package com.google.android.gms.internal;

import android.os.Binder;
import android.os.IBinder;
import android.os.IInterface;
import android.os.Parcel;
import android.os.Parcelable.Creator;
import android.os.RemoteException;
import com.google.android.gms.common.api.Status;
import java.util.Map;

public abstract interface zzacp
  extends IInterface
{
  public abstract void zzZ(Status paramStatus)
    throws RemoteException;
  
  public abstract void zza(Status paramStatus, zzacn paramzzacn)
    throws RemoteException;
  
  public abstract void zza(Status paramStatus, Map paramMap)
    throws RemoteException;
  
  public abstract void zza(Status paramStatus, byte[] paramArrayOfByte)
    throws RemoteException;
  
  public static abstract class zza
    extends Binder
    implements zzacp
  {
    public zza()
    {
      attachInterface(this, "com.google.android.gms.config.internal.IConfigCallbacks");
    }
    
    public static zzacp zzds(IBinder paramIBinder)
    {
      if (paramIBinder == null) {
        return null;
      }
      IInterface localIInterface = paramIBinder.queryLocalInterface("com.google.android.gms.config.internal.IConfigCallbacks");
      if ((localIInterface != null) && ((localIInterface instanceof zzacp))) {
        return (zzacp)localIInterface;
      }
      return new zza(paramIBinder);
    }
    
    public IBinder asBinder()
    {
      return this;
    }
    
    public boolean onTransact(int paramInt1, Parcel paramParcel1, Parcel paramParcel2, int paramInt2)
      throws RemoteException
    {
      switch (paramInt1)
      {
      default: 
        return super.onTransact(paramInt1, paramParcel1, paramParcel2, paramInt2);
      case 1598968902: 
        paramParcel2.writeString("com.google.android.gms.config.internal.IConfigCallbacks");
        return true;
      case 1: 
        paramParcel1.enforceInterface("com.google.android.gms.config.internal.IConfigCallbacks");
        if (paramParcel1.readInt() != 0) {}
        for (paramParcel2 = (Status)Status.CREATOR.createFromParcel(paramParcel1);; paramParcel2 = null)
        {
          zza(paramParcel2, paramParcel1.createByteArray());
          return true;
        }
      case 2: 
        paramParcel1.enforceInterface("com.google.android.gms.config.internal.IConfigCallbacks");
        if (paramParcel1.readInt() != 0) {}
        for (paramParcel2 = (Status)Status.CREATOR.createFromParcel(paramParcel1);; paramParcel2 = null)
        {
          zza(paramParcel2, paramParcel1.readHashMap(getClass().getClassLoader()));
          return true;
        }
      case 3: 
        paramParcel1.enforceInterface("com.google.android.gms.config.internal.IConfigCallbacks");
        if (paramParcel1.readInt() != 0) {}
        for (paramParcel1 = (Status)Status.CREATOR.createFromParcel(paramParcel1);; paramParcel1 = null)
        {
          zzZ(paramParcel1);
          return true;
        }
      }
      paramParcel1.enforceInterface("com.google.android.gms.config.internal.IConfigCallbacks");
      if (paramParcel1.readInt() != 0)
      {
        paramParcel2 = (Status)Status.CREATOR.createFromParcel(paramParcel1);
        if (paramParcel1.readInt() == 0) {
          break label258;
        }
      }
      label258:
      for (paramParcel1 = (zzacn)zzacn.CREATOR.createFromParcel(paramParcel1);; paramParcel1 = null)
      {
        zza(paramParcel2, paramParcel1);
        return true;
        paramParcel2 = null;
        break;
      }
    }
    
    private static class zza
      implements zzacp
    {
      private IBinder zzrj;
      
      zza(IBinder paramIBinder)
      {
        this.zzrj = paramIBinder;
      }
      
      public IBinder asBinder()
      {
        return this.zzrj;
      }
      
      /* Error */
      public void zzZ(Status paramStatus)
        throws RemoteException
      {
        // Byte code:
        //   0: invokestatic 31	android/os/Parcel:obtain	()Landroid/os/Parcel;
        //   3: astore_2
        //   4: aload_2
        //   5: ldc 33
        //   7: invokevirtual 37	android/os/Parcel:writeInterfaceToken	(Ljava/lang/String;)V
        //   10: aload_1
        //   11: ifnull +33 -> 44
        //   14: aload_2
        //   15: iconst_1
        //   16: invokevirtual 41	android/os/Parcel:writeInt	(I)V
        //   19: aload_1
        //   20: aload_2
        //   21: iconst_0
        //   22: invokevirtual 47	com/google/android/gms/common/api/Status:writeToParcel	(Landroid/os/Parcel;I)V
        //   25: aload_0
        //   26: getfield 18	com/google/android/gms/internal/zzacp$zza$zza:zzrj	Landroid/os/IBinder;
        //   29: iconst_3
        //   30: aload_2
        //   31: aconst_null
        //   32: iconst_1
        //   33: invokeinterface 53 5 0
        //   38: pop
        //   39: aload_2
        //   40: invokevirtual 56	android/os/Parcel:recycle	()V
        //   43: return
        //   44: aload_2
        //   45: iconst_0
        //   46: invokevirtual 41	android/os/Parcel:writeInt	(I)V
        //   49: goto -24 -> 25
        //   52: astore_1
        //   53: aload_2
        //   54: invokevirtual 56	android/os/Parcel:recycle	()V
        //   57: aload_1
        //   58: athrow
        // Local variable table:
        //   start	length	slot	name	signature
        //   0	59	0	this	zza
        //   0	59	1	paramStatus	Status
        //   3	51	2	localParcel	Parcel
        // Exception table:
        //   from	to	target	type
        //   4	10	52	finally
        //   14	25	52	finally
        //   25	39	52	finally
        //   44	49	52	finally
      }
      
      public void zza(Status paramStatus, zzacn paramzzacn)
        throws RemoteException
      {
        Parcel localParcel = Parcel.obtain();
        for (;;)
        {
          try
          {
            localParcel.writeInterfaceToken("com.google.android.gms.config.internal.IConfigCallbacks");
            if (paramStatus != null)
            {
              localParcel.writeInt(1);
              paramStatus.writeToParcel(localParcel, 0);
              if (paramzzacn != null)
              {
                localParcel.writeInt(1);
                paramzzacn.writeToParcel(localParcel, 0);
                this.zzrj.transact(4, localParcel, null, 1);
              }
            }
            else
            {
              localParcel.writeInt(0);
              continue;
            }
            localParcel.writeInt(0);
          }
          finally
          {
            localParcel.recycle();
          }
        }
      }
      
      /* Error */
      public void zza(Status paramStatus, Map paramMap)
        throws RemoteException
      {
        // Byte code:
        //   0: invokestatic 31	android/os/Parcel:obtain	()Landroid/os/Parcel;
        //   3: astore_3
        //   4: aload_3
        //   5: ldc 33
        //   7: invokevirtual 37	android/os/Parcel:writeInterfaceToken	(Ljava/lang/String;)V
        //   10: aload_1
        //   11: ifnull +38 -> 49
        //   14: aload_3
        //   15: iconst_1
        //   16: invokevirtual 41	android/os/Parcel:writeInt	(I)V
        //   19: aload_1
        //   20: aload_3
        //   21: iconst_0
        //   22: invokevirtual 47	com/google/android/gms/common/api/Status:writeToParcel	(Landroid/os/Parcel;I)V
        //   25: aload_3
        //   26: aload_2
        //   27: invokevirtual 66	android/os/Parcel:writeMap	(Ljava/util/Map;)V
        //   30: aload_0
        //   31: getfield 18	com/google/android/gms/internal/zzacp$zza$zza:zzrj	Landroid/os/IBinder;
        //   34: iconst_2
        //   35: aload_3
        //   36: aconst_null
        //   37: iconst_1
        //   38: invokeinterface 53 5 0
        //   43: pop
        //   44: aload_3
        //   45: invokevirtual 56	android/os/Parcel:recycle	()V
        //   48: return
        //   49: aload_3
        //   50: iconst_0
        //   51: invokevirtual 41	android/os/Parcel:writeInt	(I)V
        //   54: goto -29 -> 25
        //   57: astore_1
        //   58: aload_3
        //   59: invokevirtual 56	android/os/Parcel:recycle	()V
        //   62: aload_1
        //   63: athrow
        // Local variable table:
        //   start	length	slot	name	signature
        //   0	64	0	this	zza
        //   0	64	1	paramStatus	Status
        //   0	64	2	paramMap	Map
        //   3	56	3	localParcel	Parcel
        // Exception table:
        //   from	to	target	type
        //   4	10	57	finally
        //   14	25	57	finally
        //   25	44	57	finally
        //   49	54	57	finally
      }
      
      /* Error */
      public void zza(Status paramStatus, byte[] paramArrayOfByte)
        throws RemoteException
      {
        // Byte code:
        //   0: invokestatic 31	android/os/Parcel:obtain	()Landroid/os/Parcel;
        //   3: astore_3
        //   4: aload_3
        //   5: ldc 33
        //   7: invokevirtual 37	android/os/Parcel:writeInterfaceToken	(Ljava/lang/String;)V
        //   10: aload_1
        //   11: ifnull +38 -> 49
        //   14: aload_3
        //   15: iconst_1
        //   16: invokevirtual 41	android/os/Parcel:writeInt	(I)V
        //   19: aload_1
        //   20: aload_3
        //   21: iconst_0
        //   22: invokevirtual 47	com/google/android/gms/common/api/Status:writeToParcel	(Landroid/os/Parcel;I)V
        //   25: aload_3
        //   26: aload_2
        //   27: invokevirtual 71	android/os/Parcel:writeByteArray	([B)V
        //   30: aload_0
        //   31: getfield 18	com/google/android/gms/internal/zzacp$zza$zza:zzrj	Landroid/os/IBinder;
        //   34: iconst_1
        //   35: aload_3
        //   36: aconst_null
        //   37: iconst_1
        //   38: invokeinterface 53 5 0
        //   43: pop
        //   44: aload_3
        //   45: invokevirtual 56	android/os/Parcel:recycle	()V
        //   48: return
        //   49: aload_3
        //   50: iconst_0
        //   51: invokevirtual 41	android/os/Parcel:writeInt	(I)V
        //   54: goto -29 -> 25
        //   57: astore_1
        //   58: aload_3
        //   59: invokevirtual 56	android/os/Parcel:recycle	()V
        //   62: aload_1
        //   63: athrow
        // Local variable table:
        //   start	length	slot	name	signature
        //   0	64	0	this	zza
        //   0	64	1	paramStatus	Status
        //   0	64	2	paramArrayOfByte	byte[]
        //   3	56	3	localParcel	Parcel
        // Exception table:
        //   from	to	target	type
        //   4	10	57	finally
        //   14	25	57	finally
        //   25	44	57	finally
        //   49	54	57	finally
      }
    }
  }
}


/* Location:              /home/evan/Downloads/fugu-opr2.170623.027-factory-d4be396e/fugu-opr2.170623.027/image-fugu-opr2.170623.027/TVLauncher/TVLauncher/TVLauncher-dex2jar.jar!/com/google/android/gms/internal/zzacp.class
 * Java compiler version: 6 (50.0)
 * JD-Core Version:       0.7.1
 */