package com.google.android.gms.internal;

import android.os.Binder;
import android.os.IBinder;
import android.os.IInterface;
import android.os.Parcel;
import android.os.Parcelable.Creator;
import android.os.RemoteException;
import com.google.android.gms.phenotype.Configuration;
import java.util.List;

public abstract interface zzacq
  extends IInterface
{
  public abstract void zza(zzacp paramzzacp, zzacl paramzzacl)
    throws RemoteException;
  
  public abstract void zza(zzacp paramzzacp, String paramString1, Configuration paramConfiguration, String paramString2)
    throws RemoteException;
  
  public abstract void zza(zzacp paramzzacp, String paramString1, String paramString2)
    throws RemoteException;
  
  public abstract void zza(zzacp paramzzacp, String paramString, List paramList)
    throws RemoteException;
  
  public abstract void zzb(zzacp paramzzacp, String paramString1, String paramString2)
    throws RemoteException;
  
  public static abstract class zza
    extends Binder
    implements zzacq
  {
    public static zzacq zzdt(IBinder paramIBinder)
    {
      if (paramIBinder == null) {
        return null;
      }
      IInterface localIInterface = paramIBinder.queryLocalInterface("com.google.android.gms.config.internal.IConfigService");
      if ((localIInterface != null) && ((localIInterface instanceof zzacq))) {
        return (zzacq)localIInterface;
      }
      return new zza(paramIBinder);
    }
    
    public boolean onTransact(int paramInt1, Parcel paramParcel1, Parcel paramParcel2, int paramInt2)
      throws RemoteException
    {
      zzacp localzzacp = null;
      Object localObject1 = null;
      switch (paramInt1)
      {
      default: 
        return super.onTransact(paramInt1, paramParcel1, paramParcel2, paramInt2);
      case 1598968902: 
        paramParcel2.writeString("com.google.android.gms.config.internal.IConfigService");
        return true;
      case 4: 
        paramParcel1.enforceInterface("com.google.android.gms.config.internal.IConfigService");
        zza(zzacp.zza.zzds(paramParcel1.readStrongBinder()), paramParcel1.readString(), paramParcel1.readString());
        paramParcel2.writeNoException();
        return true;
      case 5: 
        paramParcel1.enforceInterface("com.google.android.gms.config.internal.IConfigService");
        zzb(zzacp.zza.zzds(paramParcel1.readStrongBinder()), paramParcel1.readString(), paramParcel1.readString());
        paramParcel2.writeNoException();
        return true;
      case 6: 
        paramParcel1.enforceInterface("com.google.android.gms.config.internal.IConfigService");
        zza(zzacp.zza.zzds(paramParcel1.readStrongBinder()), paramParcel1.readString(), paramParcel1.readArrayList(getClass().getClassLoader()));
        paramParcel2.writeNoException();
        return true;
      case 7: 
        paramParcel1.enforceInterface("com.google.android.gms.config.internal.IConfigService");
        localzzacp = zzacp.zza.zzds(paramParcel1.readStrongBinder());
        localObject2 = paramParcel1.readString();
        if (paramParcel1.readInt() != 0) {
          localObject1 = (Configuration)Configuration.CREATOR.createFromParcel(paramParcel1);
        }
        zza(localzzacp, (String)localObject2, (Configuration)localObject1, paramParcel1.readString());
        paramParcel2.writeNoException();
        return true;
      }
      paramParcel1.enforceInterface("com.google.android.gms.config.internal.IConfigService");
      Object localObject2 = zzacp.zza.zzds(paramParcel1.readStrongBinder());
      localObject1 = localzzacp;
      if (paramParcel1.readInt() != 0) {
        localObject1 = (zzacl)zzacl.CREATOR.createFromParcel(paramParcel1);
      }
      zza((zzacp)localObject2, (zzacl)localObject1);
      paramParcel2.writeNoException();
      return true;
    }
    
    private static class zza
      implements zzacq
    {
      private IBinder zzrj;
      
      zza(IBinder paramIBinder)
      {
        this.zzrj = paramIBinder;
      }
      
      public IBinder asBinder()
      {
        return this.zzrj;
      }
      
      /* Error */
      public void zza(zzacp paramzzacp, zzacl paramzzacl)
        throws RemoteException
      {
        // Byte code:
        //   0: invokestatic 30	android/os/Parcel:obtain	()Landroid/os/Parcel;
        //   3: astore_3
        //   4: invokestatic 30	android/os/Parcel:obtain	()Landroid/os/Parcel;
        //   7: astore 4
        //   9: aload_3
        //   10: ldc 32
        //   12: invokevirtual 36	android/os/Parcel:writeInterfaceToken	(Ljava/lang/String;)V
        //   15: aload_1
        //   16: ifnull +61 -> 77
        //   19: aload_1
        //   20: invokeinterface 40 1 0
        //   25: astore_1
        //   26: aload_3
        //   27: aload_1
        //   28: invokevirtual 43	android/os/Parcel:writeStrongBinder	(Landroid/os/IBinder;)V
        //   31: aload_2
        //   32: ifnull +50 -> 82
        //   35: aload_3
        //   36: iconst_1
        //   37: invokevirtual 47	android/os/Parcel:writeInt	(I)V
        //   40: aload_2
        //   41: aload_3
        //   42: iconst_0
        //   43: invokevirtual 53	com/google/android/gms/internal/zzacl:writeToParcel	(Landroid/os/Parcel;I)V
        //   46: aload_0
        //   47: getfield 18	com/google/android/gms/internal/zzacq$zza$zza:zzrj	Landroid/os/IBinder;
        //   50: bipush 8
        //   52: aload_3
        //   53: aload 4
        //   55: iconst_0
        //   56: invokeinterface 59 5 0
        //   61: pop
        //   62: aload 4
        //   64: invokevirtual 62	android/os/Parcel:readException	()V
        //   67: aload 4
        //   69: invokevirtual 65	android/os/Parcel:recycle	()V
        //   72: aload_3
        //   73: invokevirtual 65	android/os/Parcel:recycle	()V
        //   76: return
        //   77: aconst_null
        //   78: astore_1
        //   79: goto -53 -> 26
        //   82: aload_3
        //   83: iconst_0
        //   84: invokevirtual 47	android/os/Parcel:writeInt	(I)V
        //   87: goto -41 -> 46
        //   90: astore_1
        //   91: aload 4
        //   93: invokevirtual 65	android/os/Parcel:recycle	()V
        //   96: aload_3
        //   97: invokevirtual 65	android/os/Parcel:recycle	()V
        //   100: aload_1
        //   101: athrow
        // Local variable table:
        //   start	length	slot	name	signature
        //   0	102	0	this	zza
        //   0	102	1	paramzzacp	zzacp
        //   0	102	2	paramzzacl	zzacl
        //   3	94	3	localParcel1	Parcel
        //   7	85	4	localParcel2	Parcel
        // Exception table:
        //   from	to	target	type
        //   9	15	90	finally
        //   19	26	90	finally
        //   26	31	90	finally
        //   35	46	90	finally
        //   46	67	90	finally
        //   82	87	90	finally
      }
      
      /* Error */
      public void zza(zzacp paramzzacp, String paramString1, Configuration paramConfiguration, String paramString2)
        throws RemoteException
      {
        // Byte code:
        //   0: invokestatic 30	android/os/Parcel:obtain	()Landroid/os/Parcel;
        //   3: astore 5
        //   5: invokestatic 30	android/os/Parcel:obtain	()Landroid/os/Parcel;
        //   8: astore 6
        //   10: aload 5
        //   12: ldc 32
        //   14: invokevirtual 36	android/os/Parcel:writeInterfaceToken	(Ljava/lang/String;)V
        //   17: aload_1
        //   18: ifnull +79 -> 97
        //   21: aload_1
        //   22: invokeinterface 40 1 0
        //   27: astore_1
        //   28: aload 5
        //   30: aload_1
        //   31: invokevirtual 43	android/os/Parcel:writeStrongBinder	(Landroid/os/IBinder;)V
        //   34: aload 5
        //   36: aload_2
        //   37: invokevirtual 70	android/os/Parcel:writeString	(Ljava/lang/String;)V
        //   40: aload_3
        //   41: ifnull +61 -> 102
        //   44: aload 5
        //   46: iconst_1
        //   47: invokevirtual 47	android/os/Parcel:writeInt	(I)V
        //   50: aload_3
        //   51: aload 5
        //   53: iconst_0
        //   54: invokevirtual 73	com/google/android/gms/phenotype/Configuration:writeToParcel	(Landroid/os/Parcel;I)V
        //   57: aload 5
        //   59: aload 4
        //   61: invokevirtual 70	android/os/Parcel:writeString	(Ljava/lang/String;)V
        //   64: aload_0
        //   65: getfield 18	com/google/android/gms/internal/zzacq$zza$zza:zzrj	Landroid/os/IBinder;
        //   68: bipush 7
        //   70: aload 5
        //   72: aload 6
        //   74: iconst_0
        //   75: invokeinterface 59 5 0
        //   80: pop
        //   81: aload 6
        //   83: invokevirtual 62	android/os/Parcel:readException	()V
        //   86: aload 6
        //   88: invokevirtual 65	android/os/Parcel:recycle	()V
        //   91: aload 5
        //   93: invokevirtual 65	android/os/Parcel:recycle	()V
        //   96: return
        //   97: aconst_null
        //   98: astore_1
        //   99: goto -71 -> 28
        //   102: aload 5
        //   104: iconst_0
        //   105: invokevirtual 47	android/os/Parcel:writeInt	(I)V
        //   108: goto -51 -> 57
        //   111: astore_1
        //   112: aload 6
        //   114: invokevirtual 65	android/os/Parcel:recycle	()V
        //   117: aload 5
        //   119: invokevirtual 65	android/os/Parcel:recycle	()V
        //   122: aload_1
        //   123: athrow
        // Local variable table:
        //   start	length	slot	name	signature
        //   0	124	0	this	zza
        //   0	124	1	paramzzacp	zzacp
        //   0	124	2	paramString1	String
        //   0	124	3	paramConfiguration	Configuration
        //   0	124	4	paramString2	String
        //   3	115	5	localParcel1	Parcel
        //   8	105	6	localParcel2	Parcel
        // Exception table:
        //   from	to	target	type
        //   10	17	111	finally
        //   21	28	111	finally
        //   28	40	111	finally
        //   44	57	111	finally
        //   57	86	111	finally
        //   102	108	111	finally
      }
      
      /* Error */
      public void zza(zzacp paramzzacp, String paramString1, String paramString2)
        throws RemoteException
      {
        // Byte code:
        //   0: invokestatic 30	android/os/Parcel:obtain	()Landroid/os/Parcel;
        //   3: astore 4
        //   5: invokestatic 30	android/os/Parcel:obtain	()Landroid/os/Parcel;
        //   8: astore 5
        //   10: aload 4
        //   12: ldc 32
        //   14: invokevirtual 36	android/os/Parcel:writeInterfaceToken	(Ljava/lang/String;)V
        //   17: aload_1
        //   18: ifnull +60 -> 78
        //   21: aload_1
        //   22: invokeinterface 40 1 0
        //   27: astore_1
        //   28: aload 4
        //   30: aload_1
        //   31: invokevirtual 43	android/os/Parcel:writeStrongBinder	(Landroid/os/IBinder;)V
        //   34: aload 4
        //   36: aload_2
        //   37: invokevirtual 70	android/os/Parcel:writeString	(Ljava/lang/String;)V
        //   40: aload 4
        //   42: aload_3
        //   43: invokevirtual 70	android/os/Parcel:writeString	(Ljava/lang/String;)V
        //   46: aload_0
        //   47: getfield 18	com/google/android/gms/internal/zzacq$zza$zza:zzrj	Landroid/os/IBinder;
        //   50: iconst_4
        //   51: aload 4
        //   53: aload 5
        //   55: iconst_0
        //   56: invokeinterface 59 5 0
        //   61: pop
        //   62: aload 5
        //   64: invokevirtual 62	android/os/Parcel:readException	()V
        //   67: aload 5
        //   69: invokevirtual 65	android/os/Parcel:recycle	()V
        //   72: aload 4
        //   74: invokevirtual 65	android/os/Parcel:recycle	()V
        //   77: return
        //   78: aconst_null
        //   79: astore_1
        //   80: goto -52 -> 28
        //   83: astore_1
        //   84: aload 5
        //   86: invokevirtual 65	android/os/Parcel:recycle	()V
        //   89: aload 4
        //   91: invokevirtual 65	android/os/Parcel:recycle	()V
        //   94: aload_1
        //   95: athrow
        // Local variable table:
        //   start	length	slot	name	signature
        //   0	96	0	this	zza
        //   0	96	1	paramzzacp	zzacp
        //   0	96	2	paramString1	String
        //   0	96	3	paramString2	String
        //   3	87	4	localParcel1	Parcel
        //   8	77	5	localParcel2	Parcel
        // Exception table:
        //   from	to	target	type
        //   10	17	83	finally
        //   21	28	83	finally
        //   28	67	83	finally
      }
      
      /* Error */
      public void zza(zzacp paramzzacp, String paramString, List paramList)
        throws RemoteException
      {
        // Byte code:
        //   0: invokestatic 30	android/os/Parcel:obtain	()Landroid/os/Parcel;
        //   3: astore 4
        //   5: invokestatic 30	android/os/Parcel:obtain	()Landroid/os/Parcel;
        //   8: astore 5
        //   10: aload 4
        //   12: ldc 32
        //   14: invokevirtual 36	android/os/Parcel:writeInterfaceToken	(Ljava/lang/String;)V
        //   17: aload_1
        //   18: ifnull +61 -> 79
        //   21: aload_1
        //   22: invokeinterface 40 1 0
        //   27: astore_1
        //   28: aload 4
        //   30: aload_1
        //   31: invokevirtual 43	android/os/Parcel:writeStrongBinder	(Landroid/os/IBinder;)V
        //   34: aload 4
        //   36: aload_2
        //   37: invokevirtual 70	android/os/Parcel:writeString	(Ljava/lang/String;)V
        //   40: aload 4
        //   42: aload_3
        //   43: invokevirtual 79	android/os/Parcel:writeList	(Ljava/util/List;)V
        //   46: aload_0
        //   47: getfield 18	com/google/android/gms/internal/zzacq$zza$zza:zzrj	Landroid/os/IBinder;
        //   50: bipush 6
        //   52: aload 4
        //   54: aload 5
        //   56: iconst_0
        //   57: invokeinterface 59 5 0
        //   62: pop
        //   63: aload 5
        //   65: invokevirtual 62	android/os/Parcel:readException	()V
        //   68: aload 5
        //   70: invokevirtual 65	android/os/Parcel:recycle	()V
        //   73: aload 4
        //   75: invokevirtual 65	android/os/Parcel:recycle	()V
        //   78: return
        //   79: aconst_null
        //   80: astore_1
        //   81: goto -53 -> 28
        //   84: astore_1
        //   85: aload 5
        //   87: invokevirtual 65	android/os/Parcel:recycle	()V
        //   90: aload 4
        //   92: invokevirtual 65	android/os/Parcel:recycle	()V
        //   95: aload_1
        //   96: athrow
        // Local variable table:
        //   start	length	slot	name	signature
        //   0	97	0	this	zza
        //   0	97	1	paramzzacp	zzacp
        //   0	97	2	paramString	String
        //   0	97	3	paramList	List
        //   3	88	4	localParcel1	Parcel
        //   8	78	5	localParcel2	Parcel
        // Exception table:
        //   from	to	target	type
        //   10	17	84	finally
        //   21	28	84	finally
        //   28	68	84	finally
      }
      
      /* Error */
      public void zzb(zzacp paramzzacp, String paramString1, String paramString2)
        throws RemoteException
      {
        // Byte code:
        //   0: invokestatic 30	android/os/Parcel:obtain	()Landroid/os/Parcel;
        //   3: astore 4
        //   5: invokestatic 30	android/os/Parcel:obtain	()Landroid/os/Parcel;
        //   8: astore 5
        //   10: aload 4
        //   12: ldc 32
        //   14: invokevirtual 36	android/os/Parcel:writeInterfaceToken	(Ljava/lang/String;)V
        //   17: aload_1
        //   18: ifnull +60 -> 78
        //   21: aload_1
        //   22: invokeinterface 40 1 0
        //   27: astore_1
        //   28: aload 4
        //   30: aload_1
        //   31: invokevirtual 43	android/os/Parcel:writeStrongBinder	(Landroid/os/IBinder;)V
        //   34: aload 4
        //   36: aload_2
        //   37: invokevirtual 70	android/os/Parcel:writeString	(Ljava/lang/String;)V
        //   40: aload 4
        //   42: aload_3
        //   43: invokevirtual 70	android/os/Parcel:writeString	(Ljava/lang/String;)V
        //   46: aload_0
        //   47: getfield 18	com/google/android/gms/internal/zzacq$zza$zza:zzrj	Landroid/os/IBinder;
        //   50: iconst_5
        //   51: aload 4
        //   53: aload 5
        //   55: iconst_0
        //   56: invokeinterface 59 5 0
        //   61: pop
        //   62: aload 5
        //   64: invokevirtual 62	android/os/Parcel:readException	()V
        //   67: aload 5
        //   69: invokevirtual 65	android/os/Parcel:recycle	()V
        //   72: aload 4
        //   74: invokevirtual 65	android/os/Parcel:recycle	()V
        //   77: return
        //   78: aconst_null
        //   79: astore_1
        //   80: goto -52 -> 28
        //   83: astore_1
        //   84: aload 5
        //   86: invokevirtual 65	android/os/Parcel:recycle	()V
        //   89: aload 4
        //   91: invokevirtual 65	android/os/Parcel:recycle	()V
        //   94: aload_1
        //   95: athrow
        // Local variable table:
        //   start	length	slot	name	signature
        //   0	96	0	this	zza
        //   0	96	1	paramzzacp	zzacp
        //   0	96	2	paramString1	String
        //   0	96	3	paramString2	String
        //   3	87	4	localParcel1	Parcel
        //   8	77	5	localParcel2	Parcel
        // Exception table:
        //   from	to	target	type
        //   10	17	83	finally
        //   21	28	83	finally
        //   28	67	83	finally
      }
    }
  }
}


/* Location:              /home/evan/Downloads/fugu-opr2.170623.027-factory-d4be396e/fugu-opr2.170623.027/image-fugu-opr2.170623.027/TVLauncher/TVLauncher/TVLauncher-dex2jar.jar!/com/google/android/gms/internal/zzacq.class
 * Java compiler version: 6 (50.0)
 * JD-Core Version:       0.7.1
 */