package com.google.android.gms.internal;

import android.os.Binder;
import android.os.IBinder;
import android.os.IInterface;
import android.os.Parcel;
import android.os.RemoteException;

public abstract interface zzbci
  extends IInterface
{
  public abstract void zza(zzbch paramzzbch)
    throws RemoteException;
  
  public abstract void zza(zzbch paramzzbch, long paramLong)
    throws RemoteException;
  
  public abstract void zza(zzbch paramzzbch, String paramString)
    throws RemoteException;
  
  public abstract void zza(zzbch paramzzbch, String paramString, int paramInt, String[] paramArrayOfString, byte[] paramArrayOfByte)
    throws RemoteException;
  
  public abstract void zza(zzbch paramzzbch, String paramString1, int paramInt, String[] paramArrayOfString, byte[] paramArrayOfByte, String paramString2, String paramString3)
    throws RemoteException;
  
  public abstract void zza(zzbch paramzzbch, String paramString, int paramInt, String[] paramArrayOfString, int[] paramArrayOfInt, byte[] paramArrayOfByte)
    throws RemoteException;
  
  public abstract void zza(zzbch paramzzbch, String paramString1, String paramString2)
    throws RemoteException;
  
  public abstract void zza(zzbch paramzzbch, String paramString1, String paramString2, int paramInt)
    throws RemoteException;
  
  public abstract void zza(zzbch paramzzbch, String paramString1, String paramString2, String paramString3)
    throws RemoteException;
  
  public abstract void zza(zzbch paramzzbch, String paramString1, String paramString2, String paramString3, int paramInt1, int paramInt2, String paramString4)
    throws RemoteException;
  
  public abstract void zza(zzbch paramzzbch, String paramString1, String paramString2, String paramString3, String paramString4)
    throws RemoteException;
  
  public abstract void zza(zzbch paramzzbch, byte[] paramArrayOfByte)
    throws RemoteException;
  
  public abstract void zzb(zzbch paramzzbch, String paramString)
    throws RemoteException;
  
  public abstract void zzb(zzbch paramzzbch, String paramString1, String paramString2)
    throws RemoteException;
  
  public abstract void zzb(zzbch paramzzbch, String paramString1, String paramString2, String paramString3)
    throws RemoteException;
  
  public abstract void zzc(zzbch paramzzbch, String paramString)
    throws RemoteException;
  
  public abstract void zzc(zzbch paramzzbch, String paramString1, String paramString2, String paramString3)
    throws RemoteException;
  
  public static abstract class zza
    extends Binder
    implements zzbci
  {
    public static zzbci zzhu(IBinder paramIBinder)
    {
      if (paramIBinder == null) {
        return null;
      }
      IInterface localIInterface = paramIBinder.queryLocalInterface("com.google.android.gms.phenotype.internal.IPhenotypeService");
      if ((localIInterface != null) && ((localIInterface instanceof zzbci))) {
        return (zzbci)localIInterface;
      }
      return new zza(paramIBinder);
    }
    
    public boolean onTransact(int paramInt1, Parcel paramParcel1, Parcel paramParcel2, int paramInt2)
      throws RemoteException
    {
      switch (paramInt1)
      {
      default: 
        return super.onTransact(paramInt1, paramParcel1, paramParcel2, paramInt2);
      case 1598968902: 
        paramParcel2.writeString("com.google.android.gms.phenotype.internal.IPhenotypeService");
        return true;
      case 1: 
        paramParcel1.enforceInterface("com.google.android.gms.phenotype.internal.IPhenotypeService");
        zza(zzbch.zza.zzht(paramParcel1.readStrongBinder()), paramParcel1.readString(), paramParcel1.readInt(), paramParcel1.createStringArray(), paramParcel1.createByteArray());
        paramParcel2.writeNoException();
        return true;
      case 2: 
        paramParcel1.enforceInterface("com.google.android.gms.phenotype.internal.IPhenotypeService");
        zza(zzbch.zza.zzht(paramParcel1.readStrongBinder()), paramParcel1.readString(), paramParcel1.readInt(), paramParcel1.createStringArray(), paramParcel1.createIntArray(), paramParcel1.createByteArray());
        paramParcel2.writeNoException();
        return true;
      case 3: 
        paramParcel1.enforceInterface("com.google.android.gms.phenotype.internal.IPhenotypeService");
        zza(zzbch.zza.zzht(paramParcel1.readStrongBinder()), paramParcel1.readString());
        paramParcel2.writeNoException();
        return true;
      case 4: 
        paramParcel1.enforceInterface("com.google.android.gms.phenotype.internal.IPhenotypeService");
        zza(zzbch.zza.zzht(paramParcel1.readStrongBinder()), paramParcel1.readString(), paramParcel1.readString());
        paramParcel2.writeNoException();
        return true;
      case 5: 
        paramParcel1.enforceInterface("com.google.android.gms.phenotype.internal.IPhenotypeService");
        zzb(zzbch.zza.zzht(paramParcel1.readStrongBinder()), paramParcel1.readString());
        paramParcel2.writeNoException();
        return true;
      case 6: 
        paramParcel1.enforceInterface("com.google.android.gms.phenotype.internal.IPhenotypeService");
        zzb(zzbch.zza.zzht(paramParcel1.readStrongBinder()), paramParcel1.readString(), paramParcel1.readString());
        paramParcel2.writeNoException();
        return true;
      case 7: 
        paramParcel1.enforceInterface("com.google.android.gms.phenotype.internal.IPhenotypeService");
        zza(zzbch.zza.zzht(paramParcel1.readStrongBinder()));
        paramParcel2.writeNoException();
        return true;
      case 8: 
        paramParcel1.enforceInterface("com.google.android.gms.phenotype.internal.IPhenotypeService");
        zza(zzbch.zza.zzht(paramParcel1.readStrongBinder()), paramParcel1.createByteArray());
        paramParcel2.writeNoException();
        return true;
      case 9: 
        paramParcel1.enforceInterface("com.google.android.gms.phenotype.internal.IPhenotypeService");
        zza(zzbch.zza.zzht(paramParcel1.readStrongBinder()), paramParcel1.readString(), paramParcel1.readString(), paramParcel1.readInt());
        paramParcel2.writeNoException();
        return true;
      case 10: 
        paramParcel1.enforceInterface("com.google.android.gms.phenotype.internal.IPhenotypeService");
        zzc(zzbch.zza.zzht(paramParcel1.readStrongBinder()), paramParcel1.readString());
        paramParcel2.writeNoException();
        return true;
      case 11: 
        paramParcel1.enforceInterface("com.google.android.gms.phenotype.internal.IPhenotypeService");
        zza(zzbch.zza.zzht(paramParcel1.readStrongBinder()), paramParcel1.readString(), paramParcel1.readString(), paramParcel1.readString());
        paramParcel2.writeNoException();
        return true;
      case 12: 
        paramParcel1.enforceInterface("com.google.android.gms.phenotype.internal.IPhenotypeService");
        zza(zzbch.zza.zzht(paramParcel1.readStrongBinder()), paramParcel1.readLong());
        paramParcel2.writeNoException();
        return true;
      case 13: 
        paramParcel1.enforceInterface("com.google.android.gms.phenotype.internal.IPhenotypeService");
        zza(zzbch.zza.zzht(paramParcel1.readStrongBinder()), paramParcel1.readString(), paramParcel1.readInt(), paramParcel1.createStringArray(), paramParcel1.createByteArray(), paramParcel1.readString(), paramParcel1.readString());
        paramParcel2.writeNoException();
        return true;
      case 14: 
        paramParcel1.enforceInterface("com.google.android.gms.phenotype.internal.IPhenotypeService");
        zza(zzbch.zza.zzht(paramParcel1.readStrongBinder()), paramParcel1.readString(), paramParcel1.readString(), paramParcel1.readString(), paramParcel1.readInt(), paramParcel1.readInt(), paramParcel1.readString());
        paramParcel2.writeNoException();
        return true;
      case 15: 
        paramParcel1.enforceInterface("com.google.android.gms.phenotype.internal.IPhenotypeService");
        zzb(zzbch.zza.zzht(paramParcel1.readStrongBinder()), paramParcel1.readString(), paramParcel1.readString(), paramParcel1.readString());
        paramParcel2.writeNoException();
        return true;
      case 16: 
        paramParcel1.enforceInterface("com.google.android.gms.phenotype.internal.IPhenotypeService");
        zzc(zzbch.zza.zzht(paramParcel1.readStrongBinder()), paramParcel1.readString(), paramParcel1.readString(), paramParcel1.readString());
        paramParcel2.writeNoException();
        return true;
      }
      paramParcel1.enforceInterface("com.google.android.gms.phenotype.internal.IPhenotypeService");
      zza(zzbch.zza.zzht(paramParcel1.readStrongBinder()), paramParcel1.readString(), paramParcel1.readString(), paramParcel1.readString(), paramParcel1.readString());
      paramParcel2.writeNoException();
      return true;
    }
    
    private static class zza
      implements zzbci
    {
      private IBinder zzrj;
      
      zza(IBinder paramIBinder)
      {
        this.zzrj = paramIBinder;
      }
      
      public IBinder asBinder()
      {
        return this.zzrj;
      }
      
      /* Error */
      public void zza(zzbch paramzzbch)
        throws RemoteException
      {
        // Byte code:
        //   0: invokestatic 30	android/os/Parcel:obtain	()Landroid/os/Parcel;
        //   3: astore_2
        //   4: invokestatic 30	android/os/Parcel:obtain	()Landroid/os/Parcel;
        //   7: astore_3
        //   8: aload_2
        //   9: ldc 32
        //   11: invokevirtual 36	android/os/Parcel:writeInterfaceToken	(Ljava/lang/String;)V
        //   14: aload_1
        //   15: ifnull +43 -> 58
        //   18: aload_1
        //   19: invokeinterface 40 1 0
        //   24: astore_1
        //   25: aload_2
        //   26: aload_1
        //   27: invokevirtual 43	android/os/Parcel:writeStrongBinder	(Landroid/os/IBinder;)V
        //   30: aload_0
        //   31: getfield 18	com/google/android/gms/internal/zzbci$zza$zza:zzrj	Landroid/os/IBinder;
        //   34: bipush 7
        //   36: aload_2
        //   37: aload_3
        //   38: iconst_0
        //   39: invokeinterface 49 5 0
        //   44: pop
        //   45: aload_3
        //   46: invokevirtual 52	android/os/Parcel:readException	()V
        //   49: aload_3
        //   50: invokevirtual 55	android/os/Parcel:recycle	()V
        //   53: aload_2
        //   54: invokevirtual 55	android/os/Parcel:recycle	()V
        //   57: return
        //   58: aconst_null
        //   59: astore_1
        //   60: goto -35 -> 25
        //   63: astore_1
        //   64: aload_3
        //   65: invokevirtual 55	android/os/Parcel:recycle	()V
        //   68: aload_2
        //   69: invokevirtual 55	android/os/Parcel:recycle	()V
        //   72: aload_1
        //   73: athrow
        // Local variable table:
        //   start	length	slot	name	signature
        //   0	74	0	this	zza
        //   0	74	1	paramzzbch	zzbch
        //   3	66	2	localParcel1	Parcel
        //   7	58	3	localParcel2	Parcel
        // Exception table:
        //   from	to	target	type
        //   8	14	63	finally
        //   18	25	63	finally
        //   25	49	63	finally
      }
      
      /* Error */
      public void zza(zzbch paramzzbch, long paramLong)
        throws RemoteException
      {
        // Byte code:
        //   0: invokestatic 30	android/os/Parcel:obtain	()Landroid/os/Parcel;
        //   3: astore 4
        //   5: invokestatic 30	android/os/Parcel:obtain	()Landroid/os/Parcel;
        //   8: astore 5
        //   10: aload 4
        //   12: ldc 32
        //   14: invokevirtual 36	android/os/Parcel:writeInterfaceToken	(Ljava/lang/String;)V
        //   17: aload_1
        //   18: ifnull +55 -> 73
        //   21: aload_1
        //   22: invokeinterface 40 1 0
        //   27: astore_1
        //   28: aload 4
        //   30: aload_1
        //   31: invokevirtual 43	android/os/Parcel:writeStrongBinder	(Landroid/os/IBinder;)V
        //   34: aload 4
        //   36: lload_2
        //   37: invokevirtual 61	android/os/Parcel:writeLong	(J)V
        //   40: aload_0
        //   41: getfield 18	com/google/android/gms/internal/zzbci$zza$zza:zzrj	Landroid/os/IBinder;
        //   44: bipush 12
        //   46: aload 4
        //   48: aload 5
        //   50: iconst_0
        //   51: invokeinterface 49 5 0
        //   56: pop
        //   57: aload 5
        //   59: invokevirtual 52	android/os/Parcel:readException	()V
        //   62: aload 5
        //   64: invokevirtual 55	android/os/Parcel:recycle	()V
        //   67: aload 4
        //   69: invokevirtual 55	android/os/Parcel:recycle	()V
        //   72: return
        //   73: aconst_null
        //   74: astore_1
        //   75: goto -47 -> 28
        //   78: astore_1
        //   79: aload 5
        //   81: invokevirtual 55	android/os/Parcel:recycle	()V
        //   84: aload 4
        //   86: invokevirtual 55	android/os/Parcel:recycle	()V
        //   89: aload_1
        //   90: athrow
        // Local variable table:
        //   start	length	slot	name	signature
        //   0	91	0	this	zza
        //   0	91	1	paramzzbch	zzbch
        //   0	91	2	paramLong	long
        //   3	82	4	localParcel1	Parcel
        //   8	72	5	localParcel2	Parcel
        // Exception table:
        //   from	to	target	type
        //   10	17	78	finally
        //   21	28	78	finally
        //   28	62	78	finally
      }
      
      /* Error */
      public void zza(zzbch paramzzbch, String paramString)
        throws RemoteException
      {
        // Byte code:
        //   0: invokestatic 30	android/os/Parcel:obtain	()Landroid/os/Parcel;
        //   3: astore_3
        //   4: invokestatic 30	android/os/Parcel:obtain	()Landroid/os/Parcel;
        //   7: astore 4
        //   9: aload_3
        //   10: ldc 32
        //   12: invokevirtual 36	android/os/Parcel:writeInterfaceToken	(Ljava/lang/String;)V
        //   15: aload_1
        //   16: ifnull +50 -> 66
        //   19: aload_1
        //   20: invokeinterface 40 1 0
        //   25: astore_1
        //   26: aload_3
        //   27: aload_1
        //   28: invokevirtual 43	android/os/Parcel:writeStrongBinder	(Landroid/os/IBinder;)V
        //   31: aload_3
        //   32: aload_2
        //   33: invokevirtual 65	android/os/Parcel:writeString	(Ljava/lang/String;)V
        //   36: aload_0
        //   37: getfield 18	com/google/android/gms/internal/zzbci$zza$zza:zzrj	Landroid/os/IBinder;
        //   40: iconst_3
        //   41: aload_3
        //   42: aload 4
        //   44: iconst_0
        //   45: invokeinterface 49 5 0
        //   50: pop
        //   51: aload 4
        //   53: invokevirtual 52	android/os/Parcel:readException	()V
        //   56: aload 4
        //   58: invokevirtual 55	android/os/Parcel:recycle	()V
        //   61: aload_3
        //   62: invokevirtual 55	android/os/Parcel:recycle	()V
        //   65: return
        //   66: aconst_null
        //   67: astore_1
        //   68: goto -42 -> 26
        //   71: astore_1
        //   72: aload 4
        //   74: invokevirtual 55	android/os/Parcel:recycle	()V
        //   77: aload_3
        //   78: invokevirtual 55	android/os/Parcel:recycle	()V
        //   81: aload_1
        //   82: athrow
        // Local variable table:
        //   start	length	slot	name	signature
        //   0	83	0	this	zza
        //   0	83	1	paramzzbch	zzbch
        //   0	83	2	paramString	String
        //   3	75	3	localParcel1	Parcel
        //   7	66	4	localParcel2	Parcel
        // Exception table:
        //   from	to	target	type
        //   9	15	71	finally
        //   19	26	71	finally
        //   26	56	71	finally
      }
      
      /* Error */
      public void zza(zzbch paramzzbch, String paramString, int paramInt, String[] paramArrayOfString, byte[] paramArrayOfByte)
        throws RemoteException
      {
        // Byte code:
        //   0: invokestatic 30	android/os/Parcel:obtain	()Landroid/os/Parcel;
        //   3: astore 6
        //   5: invokestatic 30	android/os/Parcel:obtain	()Landroid/os/Parcel;
        //   8: astore 7
        //   10: aload 6
        //   12: ldc 32
        //   14: invokevirtual 36	android/os/Parcel:writeInterfaceToken	(Ljava/lang/String;)V
        //   17: aload_1
        //   18: ifnull +74 -> 92
        //   21: aload_1
        //   22: invokeinterface 40 1 0
        //   27: astore_1
        //   28: aload 6
        //   30: aload_1
        //   31: invokevirtual 43	android/os/Parcel:writeStrongBinder	(Landroid/os/IBinder;)V
        //   34: aload 6
        //   36: aload_2
        //   37: invokevirtual 65	android/os/Parcel:writeString	(Ljava/lang/String;)V
        //   40: aload 6
        //   42: iload_3
        //   43: invokevirtual 70	android/os/Parcel:writeInt	(I)V
        //   46: aload 6
        //   48: aload 4
        //   50: invokevirtual 74	android/os/Parcel:writeStringArray	([Ljava/lang/String;)V
        //   53: aload 6
        //   55: aload 5
        //   57: invokevirtual 78	android/os/Parcel:writeByteArray	([B)V
        //   60: aload_0
        //   61: getfield 18	com/google/android/gms/internal/zzbci$zza$zza:zzrj	Landroid/os/IBinder;
        //   64: iconst_1
        //   65: aload 6
        //   67: aload 7
        //   69: iconst_0
        //   70: invokeinterface 49 5 0
        //   75: pop
        //   76: aload 7
        //   78: invokevirtual 52	android/os/Parcel:readException	()V
        //   81: aload 7
        //   83: invokevirtual 55	android/os/Parcel:recycle	()V
        //   86: aload 6
        //   88: invokevirtual 55	android/os/Parcel:recycle	()V
        //   91: return
        //   92: aconst_null
        //   93: astore_1
        //   94: goto -66 -> 28
        //   97: astore_1
        //   98: aload 7
        //   100: invokevirtual 55	android/os/Parcel:recycle	()V
        //   103: aload 6
        //   105: invokevirtual 55	android/os/Parcel:recycle	()V
        //   108: aload_1
        //   109: athrow
        // Local variable table:
        //   start	length	slot	name	signature
        //   0	110	0	this	zza
        //   0	110	1	paramzzbch	zzbch
        //   0	110	2	paramString	String
        //   0	110	3	paramInt	int
        //   0	110	4	paramArrayOfString	String[]
        //   0	110	5	paramArrayOfByte	byte[]
        //   3	101	6	localParcel1	Parcel
        //   8	91	7	localParcel2	Parcel
        // Exception table:
        //   from	to	target	type
        //   10	17	97	finally
        //   21	28	97	finally
        //   28	81	97	finally
      }
      
      /* Error */
      public void zza(zzbch paramzzbch, String paramString1, int paramInt, String[] paramArrayOfString, byte[] paramArrayOfByte, String paramString2, String paramString3)
        throws RemoteException
      {
        // Byte code:
        //   0: invokestatic 30	android/os/Parcel:obtain	()Landroid/os/Parcel;
        //   3: astore 8
        //   5: invokestatic 30	android/os/Parcel:obtain	()Landroid/os/Parcel;
        //   8: astore 9
        //   10: aload 8
        //   12: ldc 32
        //   14: invokevirtual 36	android/os/Parcel:writeInterfaceToken	(Ljava/lang/String;)V
        //   17: aload_1
        //   18: ifnull +89 -> 107
        //   21: aload_1
        //   22: invokeinterface 40 1 0
        //   27: astore_1
        //   28: aload 8
        //   30: aload_1
        //   31: invokevirtual 43	android/os/Parcel:writeStrongBinder	(Landroid/os/IBinder;)V
        //   34: aload 8
        //   36: aload_2
        //   37: invokevirtual 65	android/os/Parcel:writeString	(Ljava/lang/String;)V
        //   40: aload 8
        //   42: iload_3
        //   43: invokevirtual 70	android/os/Parcel:writeInt	(I)V
        //   46: aload 8
        //   48: aload 4
        //   50: invokevirtual 74	android/os/Parcel:writeStringArray	([Ljava/lang/String;)V
        //   53: aload 8
        //   55: aload 5
        //   57: invokevirtual 78	android/os/Parcel:writeByteArray	([B)V
        //   60: aload 8
        //   62: aload 6
        //   64: invokevirtual 65	android/os/Parcel:writeString	(Ljava/lang/String;)V
        //   67: aload 8
        //   69: aload 7
        //   71: invokevirtual 65	android/os/Parcel:writeString	(Ljava/lang/String;)V
        //   74: aload_0
        //   75: getfield 18	com/google/android/gms/internal/zzbci$zza$zza:zzrj	Landroid/os/IBinder;
        //   78: bipush 13
        //   80: aload 8
        //   82: aload 9
        //   84: iconst_0
        //   85: invokeinterface 49 5 0
        //   90: pop
        //   91: aload 9
        //   93: invokevirtual 52	android/os/Parcel:readException	()V
        //   96: aload 9
        //   98: invokevirtual 55	android/os/Parcel:recycle	()V
        //   101: aload 8
        //   103: invokevirtual 55	android/os/Parcel:recycle	()V
        //   106: return
        //   107: aconst_null
        //   108: astore_1
        //   109: goto -81 -> 28
        //   112: astore_1
        //   113: aload 9
        //   115: invokevirtual 55	android/os/Parcel:recycle	()V
        //   118: aload 8
        //   120: invokevirtual 55	android/os/Parcel:recycle	()V
        //   123: aload_1
        //   124: athrow
        // Local variable table:
        //   start	length	slot	name	signature
        //   0	125	0	this	zza
        //   0	125	1	paramzzbch	zzbch
        //   0	125	2	paramString1	String
        //   0	125	3	paramInt	int
        //   0	125	4	paramArrayOfString	String[]
        //   0	125	5	paramArrayOfByte	byte[]
        //   0	125	6	paramString2	String
        //   0	125	7	paramString3	String
        //   3	116	8	localParcel1	Parcel
        //   8	106	9	localParcel2	Parcel
        // Exception table:
        //   from	to	target	type
        //   10	17	112	finally
        //   21	28	112	finally
        //   28	96	112	finally
      }
      
      /* Error */
      public void zza(zzbch paramzzbch, String paramString, int paramInt, String[] paramArrayOfString, int[] paramArrayOfInt, byte[] paramArrayOfByte)
        throws RemoteException
      {
        // Byte code:
        //   0: invokestatic 30	android/os/Parcel:obtain	()Landroid/os/Parcel;
        //   3: astore 7
        //   5: invokestatic 30	android/os/Parcel:obtain	()Landroid/os/Parcel;
        //   8: astore 8
        //   10: aload 7
        //   12: ldc 32
        //   14: invokevirtual 36	android/os/Parcel:writeInterfaceToken	(Ljava/lang/String;)V
        //   17: aload_1
        //   18: ifnull +81 -> 99
        //   21: aload_1
        //   22: invokeinterface 40 1 0
        //   27: astore_1
        //   28: aload 7
        //   30: aload_1
        //   31: invokevirtual 43	android/os/Parcel:writeStrongBinder	(Landroid/os/IBinder;)V
        //   34: aload 7
        //   36: aload_2
        //   37: invokevirtual 65	android/os/Parcel:writeString	(Ljava/lang/String;)V
        //   40: aload 7
        //   42: iload_3
        //   43: invokevirtual 70	android/os/Parcel:writeInt	(I)V
        //   46: aload 7
        //   48: aload 4
        //   50: invokevirtual 74	android/os/Parcel:writeStringArray	([Ljava/lang/String;)V
        //   53: aload 7
        //   55: aload 5
        //   57: invokevirtual 84	android/os/Parcel:writeIntArray	([I)V
        //   60: aload 7
        //   62: aload 6
        //   64: invokevirtual 78	android/os/Parcel:writeByteArray	([B)V
        //   67: aload_0
        //   68: getfield 18	com/google/android/gms/internal/zzbci$zza$zza:zzrj	Landroid/os/IBinder;
        //   71: iconst_2
        //   72: aload 7
        //   74: aload 8
        //   76: iconst_0
        //   77: invokeinterface 49 5 0
        //   82: pop
        //   83: aload 8
        //   85: invokevirtual 52	android/os/Parcel:readException	()V
        //   88: aload 8
        //   90: invokevirtual 55	android/os/Parcel:recycle	()V
        //   93: aload 7
        //   95: invokevirtual 55	android/os/Parcel:recycle	()V
        //   98: return
        //   99: aconst_null
        //   100: astore_1
        //   101: goto -73 -> 28
        //   104: astore_1
        //   105: aload 8
        //   107: invokevirtual 55	android/os/Parcel:recycle	()V
        //   110: aload 7
        //   112: invokevirtual 55	android/os/Parcel:recycle	()V
        //   115: aload_1
        //   116: athrow
        // Local variable table:
        //   start	length	slot	name	signature
        //   0	117	0	this	zza
        //   0	117	1	paramzzbch	zzbch
        //   0	117	2	paramString	String
        //   0	117	3	paramInt	int
        //   0	117	4	paramArrayOfString	String[]
        //   0	117	5	paramArrayOfInt	int[]
        //   0	117	6	paramArrayOfByte	byte[]
        //   3	108	7	localParcel1	Parcel
        //   8	98	8	localParcel2	Parcel
        // Exception table:
        //   from	to	target	type
        //   10	17	104	finally
        //   21	28	104	finally
        //   28	88	104	finally
      }
      
      /* Error */
      public void zza(zzbch paramzzbch, String paramString1, String paramString2)
        throws RemoteException
      {
        // Byte code:
        //   0: invokestatic 30	android/os/Parcel:obtain	()Landroid/os/Parcel;
        //   3: astore 4
        //   5: invokestatic 30	android/os/Parcel:obtain	()Landroid/os/Parcel;
        //   8: astore 5
        //   10: aload 4
        //   12: ldc 32
        //   14: invokevirtual 36	android/os/Parcel:writeInterfaceToken	(Ljava/lang/String;)V
        //   17: aload_1
        //   18: ifnull +60 -> 78
        //   21: aload_1
        //   22: invokeinterface 40 1 0
        //   27: astore_1
        //   28: aload 4
        //   30: aload_1
        //   31: invokevirtual 43	android/os/Parcel:writeStrongBinder	(Landroid/os/IBinder;)V
        //   34: aload 4
        //   36: aload_2
        //   37: invokevirtual 65	android/os/Parcel:writeString	(Ljava/lang/String;)V
        //   40: aload 4
        //   42: aload_3
        //   43: invokevirtual 65	android/os/Parcel:writeString	(Ljava/lang/String;)V
        //   46: aload_0
        //   47: getfield 18	com/google/android/gms/internal/zzbci$zza$zza:zzrj	Landroid/os/IBinder;
        //   50: iconst_4
        //   51: aload 4
        //   53: aload 5
        //   55: iconst_0
        //   56: invokeinterface 49 5 0
        //   61: pop
        //   62: aload 5
        //   64: invokevirtual 52	android/os/Parcel:readException	()V
        //   67: aload 5
        //   69: invokevirtual 55	android/os/Parcel:recycle	()V
        //   72: aload 4
        //   74: invokevirtual 55	android/os/Parcel:recycle	()V
        //   77: return
        //   78: aconst_null
        //   79: astore_1
        //   80: goto -52 -> 28
        //   83: astore_1
        //   84: aload 5
        //   86: invokevirtual 55	android/os/Parcel:recycle	()V
        //   89: aload 4
        //   91: invokevirtual 55	android/os/Parcel:recycle	()V
        //   94: aload_1
        //   95: athrow
        // Local variable table:
        //   start	length	slot	name	signature
        //   0	96	0	this	zza
        //   0	96	1	paramzzbch	zzbch
        //   0	96	2	paramString1	String
        //   0	96	3	paramString2	String
        //   3	87	4	localParcel1	Parcel
        //   8	77	5	localParcel2	Parcel
        // Exception table:
        //   from	to	target	type
        //   10	17	83	finally
        //   21	28	83	finally
        //   28	67	83	finally
      }
      
      /* Error */
      public void zza(zzbch paramzzbch, String paramString1, String paramString2, int paramInt)
        throws RemoteException
      {
        // Byte code:
        //   0: invokestatic 30	android/os/Parcel:obtain	()Landroid/os/Parcel;
        //   3: astore 5
        //   5: invokestatic 30	android/os/Parcel:obtain	()Landroid/os/Parcel;
        //   8: astore 6
        //   10: aload 5
        //   12: ldc 32
        //   14: invokevirtual 36	android/os/Parcel:writeInterfaceToken	(Ljava/lang/String;)V
        //   17: aload_1
        //   18: ifnull +68 -> 86
        //   21: aload_1
        //   22: invokeinterface 40 1 0
        //   27: astore_1
        //   28: aload 5
        //   30: aload_1
        //   31: invokevirtual 43	android/os/Parcel:writeStrongBinder	(Landroid/os/IBinder;)V
        //   34: aload 5
        //   36: aload_2
        //   37: invokevirtual 65	android/os/Parcel:writeString	(Ljava/lang/String;)V
        //   40: aload 5
        //   42: aload_3
        //   43: invokevirtual 65	android/os/Parcel:writeString	(Ljava/lang/String;)V
        //   46: aload 5
        //   48: iload 4
        //   50: invokevirtual 70	android/os/Parcel:writeInt	(I)V
        //   53: aload_0
        //   54: getfield 18	com/google/android/gms/internal/zzbci$zza$zza:zzrj	Landroid/os/IBinder;
        //   57: bipush 9
        //   59: aload 5
        //   61: aload 6
        //   63: iconst_0
        //   64: invokeinterface 49 5 0
        //   69: pop
        //   70: aload 6
        //   72: invokevirtual 52	android/os/Parcel:readException	()V
        //   75: aload 6
        //   77: invokevirtual 55	android/os/Parcel:recycle	()V
        //   80: aload 5
        //   82: invokevirtual 55	android/os/Parcel:recycle	()V
        //   85: return
        //   86: aconst_null
        //   87: astore_1
        //   88: goto -60 -> 28
        //   91: astore_1
        //   92: aload 6
        //   94: invokevirtual 55	android/os/Parcel:recycle	()V
        //   97: aload 5
        //   99: invokevirtual 55	android/os/Parcel:recycle	()V
        //   102: aload_1
        //   103: athrow
        // Local variable table:
        //   start	length	slot	name	signature
        //   0	104	0	this	zza
        //   0	104	1	paramzzbch	zzbch
        //   0	104	2	paramString1	String
        //   0	104	3	paramString2	String
        //   0	104	4	paramInt	int
        //   3	95	5	localParcel1	Parcel
        //   8	85	6	localParcel2	Parcel
        // Exception table:
        //   from	to	target	type
        //   10	17	91	finally
        //   21	28	91	finally
        //   28	75	91	finally
      }
      
      /* Error */
      public void zza(zzbch paramzzbch, String paramString1, String paramString2, String paramString3)
        throws RemoteException
      {
        // Byte code:
        //   0: invokestatic 30	android/os/Parcel:obtain	()Landroid/os/Parcel;
        //   3: astore 5
        //   5: invokestatic 30	android/os/Parcel:obtain	()Landroid/os/Parcel;
        //   8: astore 6
        //   10: aload 5
        //   12: ldc 32
        //   14: invokevirtual 36	android/os/Parcel:writeInterfaceToken	(Ljava/lang/String;)V
        //   17: aload_1
        //   18: ifnull +68 -> 86
        //   21: aload_1
        //   22: invokeinterface 40 1 0
        //   27: astore_1
        //   28: aload 5
        //   30: aload_1
        //   31: invokevirtual 43	android/os/Parcel:writeStrongBinder	(Landroid/os/IBinder;)V
        //   34: aload 5
        //   36: aload_2
        //   37: invokevirtual 65	android/os/Parcel:writeString	(Ljava/lang/String;)V
        //   40: aload 5
        //   42: aload_3
        //   43: invokevirtual 65	android/os/Parcel:writeString	(Ljava/lang/String;)V
        //   46: aload 5
        //   48: aload 4
        //   50: invokevirtual 65	android/os/Parcel:writeString	(Ljava/lang/String;)V
        //   53: aload_0
        //   54: getfield 18	com/google/android/gms/internal/zzbci$zza$zza:zzrj	Landroid/os/IBinder;
        //   57: bipush 11
        //   59: aload 5
        //   61: aload 6
        //   63: iconst_0
        //   64: invokeinterface 49 5 0
        //   69: pop
        //   70: aload 6
        //   72: invokevirtual 52	android/os/Parcel:readException	()V
        //   75: aload 6
        //   77: invokevirtual 55	android/os/Parcel:recycle	()V
        //   80: aload 5
        //   82: invokevirtual 55	android/os/Parcel:recycle	()V
        //   85: return
        //   86: aconst_null
        //   87: astore_1
        //   88: goto -60 -> 28
        //   91: astore_1
        //   92: aload 6
        //   94: invokevirtual 55	android/os/Parcel:recycle	()V
        //   97: aload 5
        //   99: invokevirtual 55	android/os/Parcel:recycle	()V
        //   102: aload_1
        //   103: athrow
        // Local variable table:
        //   start	length	slot	name	signature
        //   0	104	0	this	zza
        //   0	104	1	paramzzbch	zzbch
        //   0	104	2	paramString1	String
        //   0	104	3	paramString2	String
        //   0	104	4	paramString3	String
        //   3	95	5	localParcel1	Parcel
        //   8	85	6	localParcel2	Parcel
        // Exception table:
        //   from	to	target	type
        //   10	17	91	finally
        //   21	28	91	finally
        //   28	75	91	finally
      }
      
      /* Error */
      public void zza(zzbch paramzzbch, String paramString1, String paramString2, String paramString3, int paramInt1, int paramInt2, String paramString4)
        throws RemoteException
      {
        // Byte code:
        //   0: invokestatic 30	android/os/Parcel:obtain	()Landroid/os/Parcel;
        //   3: astore 8
        //   5: invokestatic 30	android/os/Parcel:obtain	()Landroid/os/Parcel;
        //   8: astore 9
        //   10: aload 8
        //   12: ldc 32
        //   14: invokevirtual 36	android/os/Parcel:writeInterfaceToken	(Ljava/lang/String;)V
        //   17: aload_1
        //   18: ifnull +89 -> 107
        //   21: aload_1
        //   22: invokeinterface 40 1 0
        //   27: astore_1
        //   28: aload 8
        //   30: aload_1
        //   31: invokevirtual 43	android/os/Parcel:writeStrongBinder	(Landroid/os/IBinder;)V
        //   34: aload 8
        //   36: aload_2
        //   37: invokevirtual 65	android/os/Parcel:writeString	(Ljava/lang/String;)V
        //   40: aload 8
        //   42: aload_3
        //   43: invokevirtual 65	android/os/Parcel:writeString	(Ljava/lang/String;)V
        //   46: aload 8
        //   48: aload 4
        //   50: invokevirtual 65	android/os/Parcel:writeString	(Ljava/lang/String;)V
        //   53: aload 8
        //   55: iload 5
        //   57: invokevirtual 70	android/os/Parcel:writeInt	(I)V
        //   60: aload 8
        //   62: iload 6
        //   64: invokevirtual 70	android/os/Parcel:writeInt	(I)V
        //   67: aload 8
        //   69: aload 7
        //   71: invokevirtual 65	android/os/Parcel:writeString	(Ljava/lang/String;)V
        //   74: aload_0
        //   75: getfield 18	com/google/android/gms/internal/zzbci$zza$zza:zzrj	Landroid/os/IBinder;
        //   78: bipush 14
        //   80: aload 8
        //   82: aload 9
        //   84: iconst_0
        //   85: invokeinterface 49 5 0
        //   90: pop
        //   91: aload 9
        //   93: invokevirtual 52	android/os/Parcel:readException	()V
        //   96: aload 9
        //   98: invokevirtual 55	android/os/Parcel:recycle	()V
        //   101: aload 8
        //   103: invokevirtual 55	android/os/Parcel:recycle	()V
        //   106: return
        //   107: aconst_null
        //   108: astore_1
        //   109: goto -81 -> 28
        //   112: astore_1
        //   113: aload 9
        //   115: invokevirtual 55	android/os/Parcel:recycle	()V
        //   118: aload 8
        //   120: invokevirtual 55	android/os/Parcel:recycle	()V
        //   123: aload_1
        //   124: athrow
        // Local variable table:
        //   start	length	slot	name	signature
        //   0	125	0	this	zza
        //   0	125	1	paramzzbch	zzbch
        //   0	125	2	paramString1	String
        //   0	125	3	paramString2	String
        //   0	125	4	paramString3	String
        //   0	125	5	paramInt1	int
        //   0	125	6	paramInt2	int
        //   0	125	7	paramString4	String
        //   3	116	8	localParcel1	Parcel
        //   8	106	9	localParcel2	Parcel
        // Exception table:
        //   from	to	target	type
        //   10	17	112	finally
        //   21	28	112	finally
        //   28	96	112	finally
      }
      
      /* Error */
      public void zza(zzbch paramzzbch, String paramString1, String paramString2, String paramString3, String paramString4)
        throws RemoteException
      {
        // Byte code:
        //   0: invokestatic 30	android/os/Parcel:obtain	()Landroid/os/Parcel;
        //   3: astore 6
        //   5: invokestatic 30	android/os/Parcel:obtain	()Landroid/os/Parcel;
        //   8: astore 7
        //   10: aload 6
        //   12: ldc 32
        //   14: invokevirtual 36	android/os/Parcel:writeInterfaceToken	(Ljava/lang/String;)V
        //   17: aload_1
        //   18: ifnull +75 -> 93
        //   21: aload_1
        //   22: invokeinterface 40 1 0
        //   27: astore_1
        //   28: aload 6
        //   30: aload_1
        //   31: invokevirtual 43	android/os/Parcel:writeStrongBinder	(Landroid/os/IBinder;)V
        //   34: aload 6
        //   36: aload_2
        //   37: invokevirtual 65	android/os/Parcel:writeString	(Ljava/lang/String;)V
        //   40: aload 6
        //   42: aload_3
        //   43: invokevirtual 65	android/os/Parcel:writeString	(Ljava/lang/String;)V
        //   46: aload 6
        //   48: aload 4
        //   50: invokevirtual 65	android/os/Parcel:writeString	(Ljava/lang/String;)V
        //   53: aload 6
        //   55: aload 5
        //   57: invokevirtual 65	android/os/Parcel:writeString	(Ljava/lang/String;)V
        //   60: aload_0
        //   61: getfield 18	com/google/android/gms/internal/zzbci$zza$zza:zzrj	Landroid/os/IBinder;
        //   64: bipush 17
        //   66: aload 6
        //   68: aload 7
        //   70: iconst_0
        //   71: invokeinterface 49 5 0
        //   76: pop
        //   77: aload 7
        //   79: invokevirtual 52	android/os/Parcel:readException	()V
        //   82: aload 7
        //   84: invokevirtual 55	android/os/Parcel:recycle	()V
        //   87: aload 6
        //   89: invokevirtual 55	android/os/Parcel:recycle	()V
        //   92: return
        //   93: aconst_null
        //   94: astore_1
        //   95: goto -67 -> 28
        //   98: astore_1
        //   99: aload 7
        //   101: invokevirtual 55	android/os/Parcel:recycle	()V
        //   104: aload 6
        //   106: invokevirtual 55	android/os/Parcel:recycle	()V
        //   109: aload_1
        //   110: athrow
        // Local variable table:
        //   start	length	slot	name	signature
        //   0	111	0	this	zza
        //   0	111	1	paramzzbch	zzbch
        //   0	111	2	paramString1	String
        //   0	111	3	paramString2	String
        //   0	111	4	paramString3	String
        //   0	111	5	paramString4	String
        //   3	102	6	localParcel1	Parcel
        //   8	92	7	localParcel2	Parcel
        // Exception table:
        //   from	to	target	type
        //   10	17	98	finally
        //   21	28	98	finally
        //   28	82	98	finally
      }
      
      /* Error */
      public void zza(zzbch paramzzbch, byte[] paramArrayOfByte)
        throws RemoteException
      {
        // Byte code:
        //   0: invokestatic 30	android/os/Parcel:obtain	()Landroid/os/Parcel;
        //   3: astore_3
        //   4: invokestatic 30	android/os/Parcel:obtain	()Landroid/os/Parcel;
        //   7: astore 4
        //   9: aload_3
        //   10: ldc 32
        //   12: invokevirtual 36	android/os/Parcel:writeInterfaceToken	(Ljava/lang/String;)V
        //   15: aload_1
        //   16: ifnull +51 -> 67
        //   19: aload_1
        //   20: invokeinterface 40 1 0
        //   25: astore_1
        //   26: aload_3
        //   27: aload_1
        //   28: invokevirtual 43	android/os/Parcel:writeStrongBinder	(Landroid/os/IBinder;)V
        //   31: aload_3
        //   32: aload_2
        //   33: invokevirtual 78	android/os/Parcel:writeByteArray	([B)V
        //   36: aload_0
        //   37: getfield 18	com/google/android/gms/internal/zzbci$zza$zza:zzrj	Landroid/os/IBinder;
        //   40: bipush 8
        //   42: aload_3
        //   43: aload 4
        //   45: iconst_0
        //   46: invokeinterface 49 5 0
        //   51: pop
        //   52: aload 4
        //   54: invokevirtual 52	android/os/Parcel:readException	()V
        //   57: aload 4
        //   59: invokevirtual 55	android/os/Parcel:recycle	()V
        //   62: aload_3
        //   63: invokevirtual 55	android/os/Parcel:recycle	()V
        //   66: return
        //   67: aconst_null
        //   68: astore_1
        //   69: goto -43 -> 26
        //   72: astore_1
        //   73: aload 4
        //   75: invokevirtual 55	android/os/Parcel:recycle	()V
        //   78: aload_3
        //   79: invokevirtual 55	android/os/Parcel:recycle	()V
        //   82: aload_1
        //   83: athrow
        // Local variable table:
        //   start	length	slot	name	signature
        //   0	84	0	this	zza
        //   0	84	1	paramzzbch	zzbch
        //   0	84	2	paramArrayOfByte	byte[]
        //   3	76	3	localParcel1	Parcel
        //   7	67	4	localParcel2	Parcel
        // Exception table:
        //   from	to	target	type
        //   9	15	72	finally
        //   19	26	72	finally
        //   26	57	72	finally
      }
      
      /* Error */
      public void zzb(zzbch paramzzbch, String paramString)
        throws RemoteException
      {
        // Byte code:
        //   0: invokestatic 30	android/os/Parcel:obtain	()Landroid/os/Parcel;
        //   3: astore_3
        //   4: invokestatic 30	android/os/Parcel:obtain	()Landroid/os/Parcel;
        //   7: astore 4
        //   9: aload_3
        //   10: ldc 32
        //   12: invokevirtual 36	android/os/Parcel:writeInterfaceToken	(Ljava/lang/String;)V
        //   15: aload_1
        //   16: ifnull +50 -> 66
        //   19: aload_1
        //   20: invokeinterface 40 1 0
        //   25: astore_1
        //   26: aload_3
        //   27: aload_1
        //   28: invokevirtual 43	android/os/Parcel:writeStrongBinder	(Landroid/os/IBinder;)V
        //   31: aload_3
        //   32: aload_2
        //   33: invokevirtual 65	android/os/Parcel:writeString	(Ljava/lang/String;)V
        //   36: aload_0
        //   37: getfield 18	com/google/android/gms/internal/zzbci$zza$zza:zzrj	Landroid/os/IBinder;
        //   40: iconst_5
        //   41: aload_3
        //   42: aload 4
        //   44: iconst_0
        //   45: invokeinterface 49 5 0
        //   50: pop
        //   51: aload 4
        //   53: invokevirtual 52	android/os/Parcel:readException	()V
        //   56: aload 4
        //   58: invokevirtual 55	android/os/Parcel:recycle	()V
        //   61: aload_3
        //   62: invokevirtual 55	android/os/Parcel:recycle	()V
        //   65: return
        //   66: aconst_null
        //   67: astore_1
        //   68: goto -42 -> 26
        //   71: astore_1
        //   72: aload 4
        //   74: invokevirtual 55	android/os/Parcel:recycle	()V
        //   77: aload_3
        //   78: invokevirtual 55	android/os/Parcel:recycle	()V
        //   81: aload_1
        //   82: athrow
        // Local variable table:
        //   start	length	slot	name	signature
        //   0	83	0	this	zza
        //   0	83	1	paramzzbch	zzbch
        //   0	83	2	paramString	String
        //   3	75	3	localParcel1	Parcel
        //   7	66	4	localParcel2	Parcel
        // Exception table:
        //   from	to	target	type
        //   9	15	71	finally
        //   19	26	71	finally
        //   26	56	71	finally
      }
      
      /* Error */
      public void zzb(zzbch paramzzbch, String paramString1, String paramString2)
        throws RemoteException
      {
        // Byte code:
        //   0: invokestatic 30	android/os/Parcel:obtain	()Landroid/os/Parcel;
        //   3: astore 4
        //   5: invokestatic 30	android/os/Parcel:obtain	()Landroid/os/Parcel;
        //   8: astore 5
        //   10: aload 4
        //   12: ldc 32
        //   14: invokevirtual 36	android/os/Parcel:writeInterfaceToken	(Ljava/lang/String;)V
        //   17: aload_1
        //   18: ifnull +61 -> 79
        //   21: aload_1
        //   22: invokeinterface 40 1 0
        //   27: astore_1
        //   28: aload 4
        //   30: aload_1
        //   31: invokevirtual 43	android/os/Parcel:writeStrongBinder	(Landroid/os/IBinder;)V
        //   34: aload 4
        //   36: aload_2
        //   37: invokevirtual 65	android/os/Parcel:writeString	(Ljava/lang/String;)V
        //   40: aload 4
        //   42: aload_3
        //   43: invokevirtual 65	android/os/Parcel:writeString	(Ljava/lang/String;)V
        //   46: aload_0
        //   47: getfield 18	com/google/android/gms/internal/zzbci$zza$zza:zzrj	Landroid/os/IBinder;
        //   50: bipush 6
        //   52: aload 4
        //   54: aload 5
        //   56: iconst_0
        //   57: invokeinterface 49 5 0
        //   62: pop
        //   63: aload 5
        //   65: invokevirtual 52	android/os/Parcel:readException	()V
        //   68: aload 5
        //   70: invokevirtual 55	android/os/Parcel:recycle	()V
        //   73: aload 4
        //   75: invokevirtual 55	android/os/Parcel:recycle	()V
        //   78: return
        //   79: aconst_null
        //   80: astore_1
        //   81: goto -53 -> 28
        //   84: astore_1
        //   85: aload 5
        //   87: invokevirtual 55	android/os/Parcel:recycle	()V
        //   90: aload 4
        //   92: invokevirtual 55	android/os/Parcel:recycle	()V
        //   95: aload_1
        //   96: athrow
        // Local variable table:
        //   start	length	slot	name	signature
        //   0	97	0	this	zza
        //   0	97	1	paramzzbch	zzbch
        //   0	97	2	paramString1	String
        //   0	97	3	paramString2	String
        //   3	88	4	localParcel1	Parcel
        //   8	78	5	localParcel2	Parcel
        // Exception table:
        //   from	to	target	type
        //   10	17	84	finally
        //   21	28	84	finally
        //   28	68	84	finally
      }
      
      /* Error */
      public void zzb(zzbch paramzzbch, String paramString1, String paramString2, String paramString3)
        throws RemoteException
      {
        // Byte code:
        //   0: invokestatic 30	android/os/Parcel:obtain	()Landroid/os/Parcel;
        //   3: astore 5
        //   5: invokestatic 30	android/os/Parcel:obtain	()Landroid/os/Parcel;
        //   8: astore 6
        //   10: aload 5
        //   12: ldc 32
        //   14: invokevirtual 36	android/os/Parcel:writeInterfaceToken	(Ljava/lang/String;)V
        //   17: aload_1
        //   18: ifnull +68 -> 86
        //   21: aload_1
        //   22: invokeinterface 40 1 0
        //   27: astore_1
        //   28: aload 5
        //   30: aload_1
        //   31: invokevirtual 43	android/os/Parcel:writeStrongBinder	(Landroid/os/IBinder;)V
        //   34: aload 5
        //   36: aload_2
        //   37: invokevirtual 65	android/os/Parcel:writeString	(Ljava/lang/String;)V
        //   40: aload 5
        //   42: aload_3
        //   43: invokevirtual 65	android/os/Parcel:writeString	(Ljava/lang/String;)V
        //   46: aload 5
        //   48: aload 4
        //   50: invokevirtual 65	android/os/Parcel:writeString	(Ljava/lang/String;)V
        //   53: aload_0
        //   54: getfield 18	com/google/android/gms/internal/zzbci$zza$zza:zzrj	Landroid/os/IBinder;
        //   57: bipush 15
        //   59: aload 5
        //   61: aload 6
        //   63: iconst_0
        //   64: invokeinterface 49 5 0
        //   69: pop
        //   70: aload 6
        //   72: invokevirtual 52	android/os/Parcel:readException	()V
        //   75: aload 6
        //   77: invokevirtual 55	android/os/Parcel:recycle	()V
        //   80: aload 5
        //   82: invokevirtual 55	android/os/Parcel:recycle	()V
        //   85: return
        //   86: aconst_null
        //   87: astore_1
        //   88: goto -60 -> 28
        //   91: astore_1
        //   92: aload 6
        //   94: invokevirtual 55	android/os/Parcel:recycle	()V
        //   97: aload 5
        //   99: invokevirtual 55	android/os/Parcel:recycle	()V
        //   102: aload_1
        //   103: athrow
        // Local variable table:
        //   start	length	slot	name	signature
        //   0	104	0	this	zza
        //   0	104	1	paramzzbch	zzbch
        //   0	104	2	paramString1	String
        //   0	104	3	paramString2	String
        //   0	104	4	paramString3	String
        //   3	95	5	localParcel1	Parcel
        //   8	85	6	localParcel2	Parcel
        // Exception table:
        //   from	to	target	type
        //   10	17	91	finally
        //   21	28	91	finally
        //   28	75	91	finally
      }
      
      /* Error */
      public void zzc(zzbch paramzzbch, String paramString)
        throws RemoteException
      {
        // Byte code:
        //   0: invokestatic 30	android/os/Parcel:obtain	()Landroid/os/Parcel;
        //   3: astore_3
        //   4: invokestatic 30	android/os/Parcel:obtain	()Landroid/os/Parcel;
        //   7: astore 4
        //   9: aload_3
        //   10: ldc 32
        //   12: invokevirtual 36	android/os/Parcel:writeInterfaceToken	(Ljava/lang/String;)V
        //   15: aload_1
        //   16: ifnull +51 -> 67
        //   19: aload_1
        //   20: invokeinterface 40 1 0
        //   25: astore_1
        //   26: aload_3
        //   27: aload_1
        //   28: invokevirtual 43	android/os/Parcel:writeStrongBinder	(Landroid/os/IBinder;)V
        //   31: aload_3
        //   32: aload_2
        //   33: invokevirtual 65	android/os/Parcel:writeString	(Ljava/lang/String;)V
        //   36: aload_0
        //   37: getfield 18	com/google/android/gms/internal/zzbci$zza$zza:zzrj	Landroid/os/IBinder;
        //   40: bipush 10
        //   42: aload_3
        //   43: aload 4
        //   45: iconst_0
        //   46: invokeinterface 49 5 0
        //   51: pop
        //   52: aload 4
        //   54: invokevirtual 52	android/os/Parcel:readException	()V
        //   57: aload 4
        //   59: invokevirtual 55	android/os/Parcel:recycle	()V
        //   62: aload_3
        //   63: invokevirtual 55	android/os/Parcel:recycle	()V
        //   66: return
        //   67: aconst_null
        //   68: astore_1
        //   69: goto -43 -> 26
        //   72: astore_1
        //   73: aload 4
        //   75: invokevirtual 55	android/os/Parcel:recycle	()V
        //   78: aload_3
        //   79: invokevirtual 55	android/os/Parcel:recycle	()V
        //   82: aload_1
        //   83: athrow
        // Local variable table:
        //   start	length	slot	name	signature
        //   0	84	0	this	zza
        //   0	84	1	paramzzbch	zzbch
        //   0	84	2	paramString	String
        //   3	76	3	localParcel1	Parcel
        //   7	67	4	localParcel2	Parcel
        // Exception table:
        //   from	to	target	type
        //   9	15	72	finally
        //   19	26	72	finally
        //   26	57	72	finally
      }
      
      /* Error */
      public void zzc(zzbch paramzzbch, String paramString1, String paramString2, String paramString3)
        throws RemoteException
      {
        // Byte code:
        //   0: invokestatic 30	android/os/Parcel:obtain	()Landroid/os/Parcel;
        //   3: astore 5
        //   5: invokestatic 30	android/os/Parcel:obtain	()Landroid/os/Parcel;
        //   8: astore 6
        //   10: aload 5
        //   12: ldc 32
        //   14: invokevirtual 36	android/os/Parcel:writeInterfaceToken	(Ljava/lang/String;)V
        //   17: aload_1
        //   18: ifnull +68 -> 86
        //   21: aload_1
        //   22: invokeinterface 40 1 0
        //   27: astore_1
        //   28: aload 5
        //   30: aload_1
        //   31: invokevirtual 43	android/os/Parcel:writeStrongBinder	(Landroid/os/IBinder;)V
        //   34: aload 5
        //   36: aload_2
        //   37: invokevirtual 65	android/os/Parcel:writeString	(Ljava/lang/String;)V
        //   40: aload 5
        //   42: aload_3
        //   43: invokevirtual 65	android/os/Parcel:writeString	(Ljava/lang/String;)V
        //   46: aload 5
        //   48: aload 4
        //   50: invokevirtual 65	android/os/Parcel:writeString	(Ljava/lang/String;)V
        //   53: aload_0
        //   54: getfield 18	com/google/android/gms/internal/zzbci$zza$zza:zzrj	Landroid/os/IBinder;
        //   57: bipush 16
        //   59: aload 5
        //   61: aload 6
        //   63: iconst_0
        //   64: invokeinterface 49 5 0
        //   69: pop
        //   70: aload 6
        //   72: invokevirtual 52	android/os/Parcel:readException	()V
        //   75: aload 6
        //   77: invokevirtual 55	android/os/Parcel:recycle	()V
        //   80: aload 5
        //   82: invokevirtual 55	android/os/Parcel:recycle	()V
        //   85: return
        //   86: aconst_null
        //   87: astore_1
        //   88: goto -60 -> 28
        //   91: astore_1
        //   92: aload 6
        //   94: invokevirtual 55	android/os/Parcel:recycle	()V
        //   97: aload 5
        //   99: invokevirtual 55	android/os/Parcel:recycle	()V
        //   102: aload_1
        //   103: athrow
        // Local variable table:
        //   start	length	slot	name	signature
        //   0	104	0	this	zza
        //   0	104	1	paramzzbch	zzbch
        //   0	104	2	paramString1	String
        //   0	104	3	paramString2	String
        //   0	104	4	paramString3	String
        //   3	95	5	localParcel1	Parcel
        //   8	85	6	localParcel2	Parcel
        // Exception table:
        //   from	to	target	type
        //   10	17	91	finally
        //   21	28	91	finally
        //   28	75	91	finally
      }
    }
  }
}


/* Location:              /home/evan/Downloads/fugu-opr2.170623.027-factory-d4be396e/fugu-opr2.170623.027/image-fugu-opr2.170623.027/TVLauncher/TVLauncher/TVLauncher-dex2jar.jar!/com/google/android/gms/internal/zzbci.class
 * Java compiler version: 6 (50.0)
 * JD-Core Version:       0.7.1
 */