package com.google.android.gms.internal;

import android.os.Binder;
import android.os.IBinder;
import android.os.IInterface;
import android.os.Parcel;
import android.os.Parcelable.Creator;
import android.os.RemoteException;
import com.google.android.gms.common.api.Status;
import com.google.android.gms.phenotype.Configurations;
import com.google.android.gms.phenotype.DogfoodsToken;
import com.google.android.gms.phenotype.ExperimentTokens;
import com.google.android.gms.phenotype.Flag;
import com.google.android.gms.phenotype.FlagOverrides;

public abstract interface zzbch
  extends IInterface
{
  public abstract void zza(Status paramStatus, Configurations paramConfigurations)
    throws RemoteException;
  
  public abstract void zza(Status paramStatus, DogfoodsToken paramDogfoodsToken)
    throws RemoteException;
  
  public abstract void zza(Status paramStatus, ExperimentTokens paramExperimentTokens)
    throws RemoteException;
  
  public abstract void zza(Status paramStatus, Flag paramFlag)
    throws RemoteException;
  
  public abstract void zza(Status paramStatus, FlagOverrides paramFlagOverrides)
    throws RemoteException;
  
  public abstract void zzb(Status paramStatus, Configurations paramConfigurations)
    throws RemoteException;
  
  public abstract void zzdh(Status paramStatus)
    throws RemoteException;
  
  public abstract void zzdi(Status paramStatus)
    throws RemoteException;
  
  public abstract void zzdj(Status paramStatus)
    throws RemoteException;
  
  public abstract void zzdk(Status paramStatus)
    throws RemoteException;
  
  public abstract void zzdl(Status paramStatus)
    throws RemoteException;
  
  public abstract void zzdm(Status paramStatus)
    throws RemoteException;
  
  public abstract void zzdn(Status paramStatus)
    throws RemoteException;
  
  public static abstract class zza
    extends Binder
    implements zzbch
  {
    public zza()
    {
      attachInterface(this, "com.google.android.gms.phenotype.internal.IPhenotypeCallbacks");
    }
    
    public static zzbch zzht(IBinder paramIBinder)
    {
      if (paramIBinder == null) {
        return null;
      }
      IInterface localIInterface = paramIBinder.queryLocalInterface("com.google.android.gms.phenotype.internal.IPhenotypeCallbacks");
      if ((localIInterface != null) && ((localIInterface instanceof zzbch))) {
        return (zzbch)localIInterface;
      }
      return new zza(paramIBinder);
    }
    
    public IBinder asBinder()
    {
      return this;
    }
    
    public boolean onTransact(int paramInt1, Parcel paramParcel1, Parcel paramParcel2, int paramInt2)
      throws RemoteException
    {
      switch (paramInt1)
      {
      default: 
        return super.onTransact(paramInt1, paramParcel1, paramParcel2, paramInt2);
      case 1598968902: 
        paramParcel2.writeString("com.google.android.gms.phenotype.internal.IPhenotypeCallbacks");
        return true;
      case 1: 
        paramParcel1.enforceInterface("com.google.android.gms.phenotype.internal.IPhenotypeCallbacks");
        if (paramParcel1.readInt() != 0) {}
        for (paramParcel1 = (Status)Status.CREATOR.createFromParcel(paramParcel1);; paramParcel1 = null)
        {
          zzdi(paramParcel1);
          return true;
        }
      case 2: 
        paramParcel1.enforceInterface("com.google.android.gms.phenotype.internal.IPhenotypeCallbacks");
        if (paramParcel1.readInt() != 0) {}
        for (paramParcel1 = (Status)Status.CREATOR.createFromParcel(paramParcel1);; paramParcel1 = null)
        {
          zzdj(paramParcel1);
          return true;
        }
      case 3: 
        paramParcel1.enforceInterface("com.google.android.gms.phenotype.internal.IPhenotypeCallbacks");
        if (paramParcel1.readInt() != 0) {}
        for (paramParcel1 = (Status)Status.CREATOR.createFromParcel(paramParcel1);; paramParcel1 = null)
        {
          zzdk(paramParcel1);
          return true;
        }
      case 4: 
        paramParcel1.enforceInterface("com.google.android.gms.phenotype.internal.IPhenotypeCallbacks");
        if (paramParcel1.readInt() != 0)
        {
          paramParcel2 = (Status)Status.CREATOR.createFromParcel(paramParcel1);
          if (paramParcel1.readInt() == 0) {
            break label315;
          }
        }
        for (paramParcel1 = (Configurations)Configurations.CREATOR.createFromParcel(paramParcel1);; paramParcel1 = null)
        {
          zza(paramParcel2, paramParcel1);
          return true;
          paramParcel2 = null;
          break;
        }
      case 5: 
        paramParcel1.enforceInterface("com.google.android.gms.phenotype.internal.IPhenotypeCallbacks");
        if (paramParcel1.readInt() != 0) {}
        for (paramParcel1 = (Status)Status.CREATOR.createFromParcel(paramParcel1);; paramParcel1 = null)
        {
          zzdl(paramParcel1);
          return true;
        }
      case 6: 
        paramParcel1.enforceInterface("com.google.android.gms.phenotype.internal.IPhenotypeCallbacks");
        if (paramParcel1.readInt() != 0)
        {
          paramParcel2 = (Status)Status.CREATOR.createFromParcel(paramParcel1);
          if (paramParcel1.readInt() == 0) {
            break label417;
          }
        }
        for (paramParcel1 = (ExperimentTokens)ExperimentTokens.CREATOR.createFromParcel(paramParcel1);; paramParcel1 = null)
        {
          zza(paramParcel2, paramParcel1);
          return true;
          paramParcel2 = null;
          break;
        }
      case 7: 
        paramParcel1.enforceInterface("com.google.android.gms.phenotype.internal.IPhenotypeCallbacks");
        if (paramParcel1.readInt() != 0)
        {
          paramParcel2 = (Status)Status.CREATOR.createFromParcel(paramParcel1);
          if (paramParcel1.readInt() == 0) {
            break label481;
          }
        }
        for (paramParcel1 = (DogfoodsToken)DogfoodsToken.CREATOR.createFromParcel(paramParcel1);; paramParcel1 = null)
        {
          zza(paramParcel2, paramParcel1);
          return true;
          paramParcel2 = null;
          break;
        }
      case 8: 
        paramParcel1.enforceInterface("com.google.android.gms.phenotype.internal.IPhenotypeCallbacks");
        if (paramParcel1.readInt() != 0) {}
        for (paramParcel1 = (Status)Status.CREATOR.createFromParcel(paramParcel1);; paramParcel1 = null)
        {
          zzdm(paramParcel1);
          return true;
        }
      case 9: 
        paramParcel1.enforceInterface("com.google.android.gms.phenotype.internal.IPhenotypeCallbacks");
        if (paramParcel1.readInt() != 0)
        {
          paramParcel2 = (Status)Status.CREATOR.createFromParcel(paramParcel1);
          if (paramParcel1.readInt() == 0) {
            break label583;
          }
        }
        for (paramParcel1 = (Flag)Flag.CREATOR.createFromParcel(paramParcel1);; paramParcel1 = null)
        {
          zza(paramParcel2, paramParcel1);
          return true;
          paramParcel2 = null;
          break;
        }
      case 10: 
        paramParcel1.enforceInterface("com.google.android.gms.phenotype.internal.IPhenotypeCallbacks");
        if (paramParcel1.readInt() != 0)
        {
          paramParcel2 = (Status)Status.CREATOR.createFromParcel(paramParcel1);
          if (paramParcel1.readInt() == 0) {
            break label647;
          }
        }
        for (paramParcel1 = (Configurations)Configurations.CREATOR.createFromParcel(paramParcel1);; paramParcel1 = null)
        {
          zzb(paramParcel2, paramParcel1);
          return true;
          paramParcel2 = null;
          break;
        }
      case 11: 
        paramParcel1.enforceInterface("com.google.android.gms.phenotype.internal.IPhenotypeCallbacks");
        if (paramParcel1.readInt() != 0) {}
        for (paramParcel1 = (Status)Status.CREATOR.createFromParcel(paramParcel1);; paramParcel1 = null)
        {
          zzdh(paramParcel1);
          return true;
        }
      case 12: 
        label315:
        label417:
        label481:
        label583:
        label647:
        paramParcel1.enforceInterface("com.google.android.gms.phenotype.internal.IPhenotypeCallbacks");
        if (paramParcel1.readInt() != 0) {}
        for (paramParcel1 = (Status)Status.CREATOR.createFromParcel(paramParcel1);; paramParcel1 = null)
        {
          zzdn(paramParcel1);
          return true;
        }
      }
      paramParcel1.enforceInterface("com.google.android.gms.phenotype.internal.IPhenotypeCallbacks");
      if (paramParcel1.readInt() != 0)
      {
        paramParcel2 = (Status)Status.CREATOR.createFromParcel(paramParcel1);
        if (paramParcel1.readInt() == 0) {
          break label787;
        }
      }
      label787:
      for (paramParcel1 = (FlagOverrides)FlagOverrides.CREATOR.createFromParcel(paramParcel1);; paramParcel1 = null)
      {
        zza(paramParcel2, paramParcel1);
        return true;
        paramParcel2 = null;
        break;
      }
    }
    
    private static class zza
      implements zzbch
    {
      private IBinder zzrj;
      
      zza(IBinder paramIBinder)
      {
        this.zzrj = paramIBinder;
      }
      
      public IBinder asBinder()
      {
        return this.zzrj;
      }
      
      public void zza(Status paramStatus, Configurations paramConfigurations)
        throws RemoteException
      {
        Parcel localParcel = Parcel.obtain();
        for (;;)
        {
          try
          {
            localParcel.writeInterfaceToken("com.google.android.gms.phenotype.internal.IPhenotypeCallbacks");
            if (paramStatus != null)
            {
              localParcel.writeInt(1);
              paramStatus.writeToParcel(localParcel, 0);
              if (paramConfigurations != null)
              {
                localParcel.writeInt(1);
                paramConfigurations.writeToParcel(localParcel, 0);
                this.zzrj.transact(4, localParcel, null, 1);
              }
            }
            else
            {
              localParcel.writeInt(0);
              continue;
            }
            localParcel.writeInt(0);
          }
          finally
          {
            localParcel.recycle();
          }
        }
      }
      
      public void zza(Status paramStatus, DogfoodsToken paramDogfoodsToken)
        throws RemoteException
      {
        Parcel localParcel = Parcel.obtain();
        for (;;)
        {
          try
          {
            localParcel.writeInterfaceToken("com.google.android.gms.phenotype.internal.IPhenotypeCallbacks");
            if (paramStatus != null)
            {
              localParcel.writeInt(1);
              paramStatus.writeToParcel(localParcel, 0);
              if (paramDogfoodsToken != null)
              {
                localParcel.writeInt(1);
                paramDogfoodsToken.writeToParcel(localParcel, 0);
                this.zzrj.transact(7, localParcel, null, 1);
              }
            }
            else
            {
              localParcel.writeInt(0);
              continue;
            }
            localParcel.writeInt(0);
          }
          finally
          {
            localParcel.recycle();
          }
        }
      }
      
      public void zza(Status paramStatus, ExperimentTokens paramExperimentTokens)
        throws RemoteException
      {
        Parcel localParcel = Parcel.obtain();
        for (;;)
        {
          try
          {
            localParcel.writeInterfaceToken("com.google.android.gms.phenotype.internal.IPhenotypeCallbacks");
            if (paramStatus != null)
            {
              localParcel.writeInt(1);
              paramStatus.writeToParcel(localParcel, 0);
              if (paramExperimentTokens != null)
              {
                localParcel.writeInt(1);
                paramExperimentTokens.writeToParcel(localParcel, 0);
                this.zzrj.transact(6, localParcel, null, 1);
              }
            }
            else
            {
              localParcel.writeInt(0);
              continue;
            }
            localParcel.writeInt(0);
          }
          finally
          {
            localParcel.recycle();
          }
        }
      }
      
      public void zza(Status paramStatus, Flag paramFlag)
        throws RemoteException
      {
        Parcel localParcel = Parcel.obtain();
        for (;;)
        {
          try
          {
            localParcel.writeInterfaceToken("com.google.android.gms.phenotype.internal.IPhenotypeCallbacks");
            if (paramStatus != null)
            {
              localParcel.writeInt(1);
              paramStatus.writeToParcel(localParcel, 0);
              if (paramFlag != null)
              {
                localParcel.writeInt(1);
                paramFlag.writeToParcel(localParcel, 0);
                this.zzrj.transact(9, localParcel, null, 1);
              }
            }
            else
            {
              localParcel.writeInt(0);
              continue;
            }
            localParcel.writeInt(0);
          }
          finally
          {
            localParcel.recycle();
          }
        }
      }
      
      public void zza(Status paramStatus, FlagOverrides paramFlagOverrides)
        throws RemoteException
      {
        Parcel localParcel = Parcel.obtain();
        for (;;)
        {
          try
          {
            localParcel.writeInterfaceToken("com.google.android.gms.phenotype.internal.IPhenotypeCallbacks");
            if (paramStatus != null)
            {
              localParcel.writeInt(1);
              paramStatus.writeToParcel(localParcel, 0);
              if (paramFlagOverrides != null)
              {
                localParcel.writeInt(1);
                paramFlagOverrides.writeToParcel(localParcel, 0);
                this.zzrj.transact(13, localParcel, null, 1);
              }
            }
            else
            {
              localParcel.writeInt(0);
              continue;
            }
            localParcel.writeInt(0);
          }
          finally
          {
            localParcel.recycle();
          }
        }
      }
      
      public void zzb(Status paramStatus, Configurations paramConfigurations)
        throws RemoteException
      {
        Parcel localParcel = Parcel.obtain();
        for (;;)
        {
          try
          {
            localParcel.writeInterfaceToken("com.google.android.gms.phenotype.internal.IPhenotypeCallbacks");
            if (paramStatus != null)
            {
              localParcel.writeInt(1);
              paramStatus.writeToParcel(localParcel, 0);
              if (paramConfigurations != null)
              {
                localParcel.writeInt(1);
                paramConfigurations.writeToParcel(localParcel, 0);
                this.zzrj.transact(10, localParcel, null, 1);
              }
            }
            else
            {
              localParcel.writeInt(0);
              continue;
            }
            localParcel.writeInt(0);
          }
          finally
          {
            localParcel.recycle();
          }
        }
      }
      
      /* Error */
      public void zzdh(Status paramStatus)
        throws RemoteException
      {
        // Byte code:
        //   0: invokestatic 30	android/os/Parcel:obtain	()Landroid/os/Parcel;
        //   3: astore_2
        //   4: aload_2
        //   5: ldc 32
        //   7: invokevirtual 36	android/os/Parcel:writeInterfaceToken	(Ljava/lang/String;)V
        //   10: aload_1
        //   11: ifnull +34 -> 45
        //   14: aload_2
        //   15: iconst_1
        //   16: invokevirtual 40	android/os/Parcel:writeInt	(I)V
        //   19: aload_1
        //   20: aload_2
        //   21: iconst_0
        //   22: invokevirtual 46	com/google/android/gms/common/api/Status:writeToParcel	(Landroid/os/Parcel;I)V
        //   25: aload_0
        //   26: getfield 18	com/google/android/gms/internal/zzbch$zza$zza:zzrj	Landroid/os/IBinder;
        //   29: bipush 11
        //   31: aload_2
        //   32: aconst_null
        //   33: iconst_1
        //   34: invokeinterface 55 5 0
        //   39: pop
        //   40: aload_2
        //   41: invokevirtual 58	android/os/Parcel:recycle	()V
        //   44: return
        //   45: aload_2
        //   46: iconst_0
        //   47: invokevirtual 40	android/os/Parcel:writeInt	(I)V
        //   50: goto -25 -> 25
        //   53: astore_1
        //   54: aload_2
        //   55: invokevirtual 58	android/os/Parcel:recycle	()V
        //   58: aload_1
        //   59: athrow
        // Local variable table:
        //   start	length	slot	name	signature
        //   0	60	0	this	zza
        //   0	60	1	paramStatus	Status
        //   3	52	2	localParcel	Parcel
        // Exception table:
        //   from	to	target	type
        //   4	10	53	finally
        //   14	25	53	finally
        //   25	40	53	finally
        //   45	50	53	finally
      }
      
      /* Error */
      public void zzdi(Status paramStatus)
        throws RemoteException
      {
        // Byte code:
        //   0: invokestatic 30	android/os/Parcel:obtain	()Landroid/os/Parcel;
        //   3: astore_2
        //   4: aload_2
        //   5: ldc 32
        //   7: invokevirtual 36	android/os/Parcel:writeInterfaceToken	(Ljava/lang/String;)V
        //   10: aload_1
        //   11: ifnull +33 -> 44
        //   14: aload_2
        //   15: iconst_1
        //   16: invokevirtual 40	android/os/Parcel:writeInt	(I)V
        //   19: aload_1
        //   20: aload_2
        //   21: iconst_0
        //   22: invokevirtual 46	com/google/android/gms/common/api/Status:writeToParcel	(Landroid/os/Parcel;I)V
        //   25: aload_0
        //   26: getfield 18	com/google/android/gms/internal/zzbch$zza$zza:zzrj	Landroid/os/IBinder;
        //   29: iconst_1
        //   30: aload_2
        //   31: aconst_null
        //   32: iconst_1
        //   33: invokeinterface 55 5 0
        //   38: pop
        //   39: aload_2
        //   40: invokevirtual 58	android/os/Parcel:recycle	()V
        //   43: return
        //   44: aload_2
        //   45: iconst_0
        //   46: invokevirtual 40	android/os/Parcel:writeInt	(I)V
        //   49: goto -24 -> 25
        //   52: astore_1
        //   53: aload_2
        //   54: invokevirtual 58	android/os/Parcel:recycle	()V
        //   57: aload_1
        //   58: athrow
        // Local variable table:
        //   start	length	slot	name	signature
        //   0	59	0	this	zza
        //   0	59	1	paramStatus	Status
        //   3	51	2	localParcel	Parcel
        // Exception table:
        //   from	to	target	type
        //   4	10	52	finally
        //   14	25	52	finally
        //   25	39	52	finally
        //   44	49	52	finally
      }
      
      /* Error */
      public void zzdj(Status paramStatus)
        throws RemoteException
      {
        // Byte code:
        //   0: invokestatic 30	android/os/Parcel:obtain	()Landroid/os/Parcel;
        //   3: astore_2
        //   4: aload_2
        //   5: ldc 32
        //   7: invokevirtual 36	android/os/Parcel:writeInterfaceToken	(Ljava/lang/String;)V
        //   10: aload_1
        //   11: ifnull +33 -> 44
        //   14: aload_2
        //   15: iconst_1
        //   16: invokevirtual 40	android/os/Parcel:writeInt	(I)V
        //   19: aload_1
        //   20: aload_2
        //   21: iconst_0
        //   22: invokevirtual 46	com/google/android/gms/common/api/Status:writeToParcel	(Landroid/os/Parcel;I)V
        //   25: aload_0
        //   26: getfield 18	com/google/android/gms/internal/zzbch$zza$zza:zzrj	Landroid/os/IBinder;
        //   29: iconst_2
        //   30: aload_2
        //   31: aconst_null
        //   32: iconst_1
        //   33: invokeinterface 55 5 0
        //   38: pop
        //   39: aload_2
        //   40: invokevirtual 58	android/os/Parcel:recycle	()V
        //   43: return
        //   44: aload_2
        //   45: iconst_0
        //   46: invokevirtual 40	android/os/Parcel:writeInt	(I)V
        //   49: goto -24 -> 25
        //   52: astore_1
        //   53: aload_2
        //   54: invokevirtual 58	android/os/Parcel:recycle	()V
        //   57: aload_1
        //   58: athrow
        // Local variable table:
        //   start	length	slot	name	signature
        //   0	59	0	this	zza
        //   0	59	1	paramStatus	Status
        //   3	51	2	localParcel	Parcel
        // Exception table:
        //   from	to	target	type
        //   4	10	52	finally
        //   14	25	52	finally
        //   25	39	52	finally
        //   44	49	52	finally
      }
      
      /* Error */
      public void zzdk(Status paramStatus)
        throws RemoteException
      {
        // Byte code:
        //   0: invokestatic 30	android/os/Parcel:obtain	()Landroid/os/Parcel;
        //   3: astore_2
        //   4: aload_2
        //   5: ldc 32
        //   7: invokevirtual 36	android/os/Parcel:writeInterfaceToken	(Ljava/lang/String;)V
        //   10: aload_1
        //   11: ifnull +33 -> 44
        //   14: aload_2
        //   15: iconst_1
        //   16: invokevirtual 40	android/os/Parcel:writeInt	(I)V
        //   19: aload_1
        //   20: aload_2
        //   21: iconst_0
        //   22: invokevirtual 46	com/google/android/gms/common/api/Status:writeToParcel	(Landroid/os/Parcel;I)V
        //   25: aload_0
        //   26: getfield 18	com/google/android/gms/internal/zzbch$zza$zza:zzrj	Landroid/os/IBinder;
        //   29: iconst_3
        //   30: aload_2
        //   31: aconst_null
        //   32: iconst_1
        //   33: invokeinterface 55 5 0
        //   38: pop
        //   39: aload_2
        //   40: invokevirtual 58	android/os/Parcel:recycle	()V
        //   43: return
        //   44: aload_2
        //   45: iconst_0
        //   46: invokevirtual 40	android/os/Parcel:writeInt	(I)V
        //   49: goto -24 -> 25
        //   52: astore_1
        //   53: aload_2
        //   54: invokevirtual 58	android/os/Parcel:recycle	()V
        //   57: aload_1
        //   58: athrow
        // Local variable table:
        //   start	length	slot	name	signature
        //   0	59	0	this	zza
        //   0	59	1	paramStatus	Status
        //   3	51	2	localParcel	Parcel
        // Exception table:
        //   from	to	target	type
        //   4	10	52	finally
        //   14	25	52	finally
        //   25	39	52	finally
        //   44	49	52	finally
      }
      
      /* Error */
      public void zzdl(Status paramStatus)
        throws RemoteException
      {
        // Byte code:
        //   0: invokestatic 30	android/os/Parcel:obtain	()Landroid/os/Parcel;
        //   3: astore_2
        //   4: aload_2
        //   5: ldc 32
        //   7: invokevirtual 36	android/os/Parcel:writeInterfaceToken	(Ljava/lang/String;)V
        //   10: aload_1
        //   11: ifnull +33 -> 44
        //   14: aload_2
        //   15: iconst_1
        //   16: invokevirtual 40	android/os/Parcel:writeInt	(I)V
        //   19: aload_1
        //   20: aload_2
        //   21: iconst_0
        //   22: invokevirtual 46	com/google/android/gms/common/api/Status:writeToParcel	(Landroid/os/Parcel;I)V
        //   25: aload_0
        //   26: getfield 18	com/google/android/gms/internal/zzbch$zza$zza:zzrj	Landroid/os/IBinder;
        //   29: iconst_5
        //   30: aload_2
        //   31: aconst_null
        //   32: iconst_1
        //   33: invokeinterface 55 5 0
        //   38: pop
        //   39: aload_2
        //   40: invokevirtual 58	android/os/Parcel:recycle	()V
        //   43: return
        //   44: aload_2
        //   45: iconst_0
        //   46: invokevirtual 40	android/os/Parcel:writeInt	(I)V
        //   49: goto -24 -> 25
        //   52: astore_1
        //   53: aload_2
        //   54: invokevirtual 58	android/os/Parcel:recycle	()V
        //   57: aload_1
        //   58: athrow
        // Local variable table:
        //   start	length	slot	name	signature
        //   0	59	0	this	zza
        //   0	59	1	paramStatus	Status
        //   3	51	2	localParcel	Parcel
        // Exception table:
        //   from	to	target	type
        //   4	10	52	finally
        //   14	25	52	finally
        //   25	39	52	finally
        //   44	49	52	finally
      }
      
      /* Error */
      public void zzdm(Status paramStatus)
        throws RemoteException
      {
        // Byte code:
        //   0: invokestatic 30	android/os/Parcel:obtain	()Landroid/os/Parcel;
        //   3: astore_2
        //   4: aload_2
        //   5: ldc 32
        //   7: invokevirtual 36	android/os/Parcel:writeInterfaceToken	(Ljava/lang/String;)V
        //   10: aload_1
        //   11: ifnull +34 -> 45
        //   14: aload_2
        //   15: iconst_1
        //   16: invokevirtual 40	android/os/Parcel:writeInt	(I)V
        //   19: aload_1
        //   20: aload_2
        //   21: iconst_0
        //   22: invokevirtual 46	com/google/android/gms/common/api/Status:writeToParcel	(Landroid/os/Parcel;I)V
        //   25: aload_0
        //   26: getfield 18	com/google/android/gms/internal/zzbch$zza$zza:zzrj	Landroid/os/IBinder;
        //   29: bipush 8
        //   31: aload_2
        //   32: aconst_null
        //   33: iconst_1
        //   34: invokeinterface 55 5 0
        //   39: pop
        //   40: aload_2
        //   41: invokevirtual 58	android/os/Parcel:recycle	()V
        //   44: return
        //   45: aload_2
        //   46: iconst_0
        //   47: invokevirtual 40	android/os/Parcel:writeInt	(I)V
        //   50: goto -25 -> 25
        //   53: astore_1
        //   54: aload_2
        //   55: invokevirtual 58	android/os/Parcel:recycle	()V
        //   58: aload_1
        //   59: athrow
        // Local variable table:
        //   start	length	slot	name	signature
        //   0	60	0	this	zza
        //   0	60	1	paramStatus	Status
        //   3	52	2	localParcel	Parcel
        // Exception table:
        //   from	to	target	type
        //   4	10	53	finally
        //   14	25	53	finally
        //   25	40	53	finally
        //   45	50	53	finally
      }
      
      /* Error */
      public void zzdn(Status paramStatus)
        throws RemoteException
      {
        // Byte code:
        //   0: invokestatic 30	android/os/Parcel:obtain	()Landroid/os/Parcel;
        //   3: astore_2
        //   4: aload_2
        //   5: ldc 32
        //   7: invokevirtual 36	android/os/Parcel:writeInterfaceToken	(Ljava/lang/String;)V
        //   10: aload_1
        //   11: ifnull +34 -> 45
        //   14: aload_2
        //   15: iconst_1
        //   16: invokevirtual 40	android/os/Parcel:writeInt	(I)V
        //   19: aload_1
        //   20: aload_2
        //   21: iconst_0
        //   22: invokevirtual 46	com/google/android/gms/common/api/Status:writeToParcel	(Landroid/os/Parcel;I)V
        //   25: aload_0
        //   26: getfield 18	com/google/android/gms/internal/zzbch$zza$zza:zzrj	Landroid/os/IBinder;
        //   29: bipush 12
        //   31: aload_2
        //   32: aconst_null
        //   33: iconst_1
        //   34: invokeinterface 55 5 0
        //   39: pop
        //   40: aload_2
        //   41: invokevirtual 58	android/os/Parcel:recycle	()V
        //   44: return
        //   45: aload_2
        //   46: iconst_0
        //   47: invokevirtual 40	android/os/Parcel:writeInt	(I)V
        //   50: goto -25 -> 25
        //   53: astore_1
        //   54: aload_2
        //   55: invokevirtual 58	android/os/Parcel:recycle	()V
        //   58: aload_1
        //   59: athrow
        // Local variable table:
        //   start	length	slot	name	signature
        //   0	60	0	this	zza
        //   0	60	1	paramStatus	Status
        //   3	52	2	localParcel	Parcel
        // Exception table:
        //   from	to	target	type
        //   4	10	53	finally
        //   14	25	53	finally
        //   25	40	53	finally
        //   45	50	53	finally
      }
    }
  }
}


/* Location:              /home/evan/Downloads/fugu-opr2.170623.027-factory-d4be396e/fugu-opr2.170623.027/image-fugu-opr2.170623.027/TVLauncher/TVLauncher/TVLauncher-dex2jar.jar!/com/google/android/gms/internal/zzbch.class
 * Java compiler version: 6 (50.0)
 * JD-Core Version:       0.7.1
 */